{
  "site": {
    "url": "https://mirror.iscas.ac.cn",
    "logo": "https://isrc.iscas.ac.cn/images/iscas-logo.jpg",
    "logo_darkmode": "https://isrc.iscas.ac.cn/images/iscas-logo.jpg",
    "abbr": "ISRC-ISCAS",
    "name": "ISCAS 镜像站",
    "homepage": "https://isrc.iscas.ac.cn",
    "request": "https://github.com/isrc-cas/mirror-requests/issues/new/choose",
    "email": "jiayi@iscas.ac.cn",
    "disk": "217/466T",
    "note": "OpenSource Mirrors | CSTNET | ISCAS",
    "big": "https://mirror.iscas.ac.cn/mirror-speedtest/1000mb.bin"
  },
  "info": [],
  "mirrors": [
    {
      "cname": "adobe-fonts",
      "desc": "Adobe 公司的开源字体",
      "url": "/adobe-fonts",
      "status": "S1675513662X1675520862",
      "help": "",
      "upstream": "rsync://mirrors.bfsu.edu.cn/adobe-fonts/",
      "size": "56.90G"
    },
    {
      "cname": "almalinux",
      "desc": "",
      "url": "/almalinux",
      "status": "S1675514290X1675528690",
      "help": "",
      "upstream": "rsync://rsync.repo.almalinux.org/almalinux/",
      "size": "1.10T"
    },
    {
      "cname": "alpine",
      "desc": "Alpine Linux 的安装镜像和官方软件包仓库",
      "url": "/alpine",
      "status": "S1675504879X1675519279",
      "help": "/help/alpine/",
      "upstream": "rsync://rsync.alpinelinux.org/alpine/",
      "size": "2.09T"
    },
    {
      "cname": "anthon",
      "desc": "Anthon Linux（安同 Linux）的安装镜像和官方软件包仓库",
      "url": "/anthon",
      "status": "S1675514768X1675529168",
      "help": "/help/anthon/",
      "upstream": "rsync://mirror.anthonos.org/anthon/",
      "size": "600.88G"
    },
    {
      "cname": "aosp-monthly",
      "desc": "AOSP （Android 系统源码）镜像每月打包",
      "url": "/aosp-monthly",
      "status": "S1675513514X1675520714",
      "help": "",
      "upstream": "rsync://mirrors.bfsu.edu.cn/aosp-monthly/",
      "size": "139.35G"
    },
    {
      "cname": "apache",
      "desc": "Apache 基金会赞助的各个项目",
      "url": "/apache",
      "status": "Y1675511884O1675497482",
      "help": "",
      "upstream": "rsync://rsync.apache.org/apache-dist/",
      "size": "185.90G"
    },
    {
      "cname": "arch4edu",
      "desc": "用于 Arch Linux 和 Arch Linux ARM 的非官方软件仓库，主要包含科研、教学所需的各种常用软件",
      "url": "/arch4edu",
      "status": "S1675515694X1675522894",
      "help": "/help/arch4edu/",
      "upstream": "rsync://mirrors.bfsu.edu.cn/arch4edu/",
      "size": "38.64G"
    },
    {
      "cname": "archlinux",
      "desc": "Arch Linux 的安装镜像和官方软件包仓库",
      "url": "/archlinux",
      "status": "S1675516188X1675523388",
      "help": "/help/archlinux/",
      "upstream": "rsync://mirrors.bfsu.edu.cn/archlinux/",
      "size": "87.32G"
    },
    {
      "cname": "archlinuxarm",
      "desc": "用于 ARM 平台的 Arch Linux 镜像和软件包仓库",
      "url": "/archlinuxarm",
      "status": "S1675508295X1675515495",
      "help": "/help/archlinuxarm/",
      "upstream": "rsync://mirrors.tuna.tsinghua.edu.cn/archlinuxarm/",
      "size": "98.01G"
    },
    {
      "cname": "archlinuxcn",
      "desc": "由 Arch Linux 中文社区驱动的非官方用户仓库，包含中文用户常用软件、工具、字体/美化包等",
      "url": "/archlinuxcn",
      "status": "S1675515751X1675522951",
      "help": "/help/archlinuxcn/",
      "upstream": "rsync://mirrors.bfsu.edu.cn/archlinuxcn/",
      "size": "101.59G"
    },
    {
      "cname": "archriscv",
      "desc": "",
      "url": "/archriscv",
      "status": "S1675513947X1675528347",
      "help": "",
      "upstream": "rsync://archriscv.felixc.at/archriscv/",
      "size": "53.24G"
    },
    {
      "cname": "armbian",
      "desc": "Armbian（面向 ARM 单板机的发行版）的软件源",
      "url": "/armbian",
      "status": "S1675502759X1675517159",
      "help": "",
      "upstream": "rsync://rsync.armbian.com/apt/",
      "size": "122.91G"
    },
    {
      "cname": "armbian-releases",
      "desc": "Armbian 的安装镜像",
      "url": "/armbian-releases",
      "status": "S1675513061X1675527461",
      "help": "",
      "upstream": "rsync://rsync.armbian.com/dl/",
      "size": "427.60G"
    },
    {
      "cname": "artixlinux",
      "desc": "Artix Linux 的官方软件包仓库（基于 Arch Linux 的不使用 systemd 的发行版）",
      "url": "/artixlinux",
      "status": "S1675505074X1675519474",
      "help": "",
      "upstream": "rsync://mirror1.artixlinux.org/artix-linux/",
      "size": "24.56G"
    },
    {
      "cname": "artixlinux-iso",
      "desc": "Artix Linux 的安装镜像",
      "url": "/artixlinux-iso",
      "status": "S1675513010X1675527410",
      "help": "",
      "upstream": "rsync://download.artixlinux.org/iso/",
      "size": "44.47G"
    },
    {
      "cname": "bioarchlinux",
      "desc": "",
      "url": "/BioArchLinux",
      "status": "S1675505072X1675519472",
      "help": "",
      "upstream": "rsync://bioarchlinux.org/sync/",
      "size": "63.57G"
    },
    {
      "cname": "bioconductor",
      "desc": "开源的基因数据分析处理工具",
      "url": "/bioconductor",
      "status": "S1675508835X1675516035",
      "help": "/help/bioconductor/",
      "upstream": "rsync://mirrors.tuna.tsinghua.edu.cn/bioconductor/",
      "size": "544.28G"
    },
    {
      "cname": "bjlx",
      "desc": "北京龙芯 & Debian 俱乐部 的公开软件源",
      "url": "/bjlx",
      "status": "S1675512625X1675527025",
      "help": "",
      "upstream": "rsync://rsync.anheng.com.cn/bjlx/",
      "size": "3.93G"
    },
    {
      "cname": "blackarch",
      "desc": "用于安全评估的基于 Arch Linux 的轻量级发行版",
      "url": "/blackarch",
      "status": "S1675504517X1675518917",
      "help": "",
      "upstream": "rsync://www.blackarch.org/blackarch/",
      "size": "79.83G"
    },
    {
      "cname": "blender",
      "desc": "专业的三维计算机图形软件",
      "url": "/blender",
      "status": "S1675513003X1675527403",
      "help": "",
      "upstream": "rsync://mirrors.dotsrc.org/blender/",
      "size": "174.14G"
    },
    {
      "cname": "calculate",
      "desc": "",
      "url": "/calculate",
      "status": "S1675491093X1675519893",
      "help": "",
      "upstream": "rsync://mirror.calculate-linux.org/calculate-all/",
      "size": "132.64G"
    },
    {
      "cname": "calculate-testing",
      "desc": "",
      "url": "/calculate-testing",
      "status": "Y1675511524O1675468324",
      "help": "",
      "upstream": "rsync://mirror.calculate-linux.org/testing/",
      "size": "40.23G"
    },
    {
      "cname": "cc",
      "desc": "CERN CentOS",
      "url": "/cc",
      "status": "Y1675463154",
      "help": "",
      "upstream": "rsync://linuxsoft.cern.ch/cc/",
      "size": "unknown"
    },
    {
      "cname": "centos",
      "desc": "CentOS 的安装镜像和官方软件包仓库",
      "url": "/centos",
      "status": "S1675514842X1675522042",
      "help": "/help/centos/",
      "upstream": "rsync://mirrors.tuna.tsinghua.edu.cn/centos/",
      "size": "552.76G"
    },
    {
      "cname": "centos-altarch",
      "desc": "CentOS 额外平台的安装镜像和官方软件包仓库",
      "url": "/centos-altarch",
      "status": "S1675514274X1675521474",
      "help": "/help/centos-altarch/",
      "upstream": "rsync://mirrors.tuna.tsinghua.edu.cn/centos-altarch/",
      "size": "305.80G"
    },
    {
      "cname": "centos-cloud",
      "desc": "",
      "url": "/centos-cloud",
      "status": "S1675471964X1675479164",
      "help": "",
      "upstream": "rsync://mirrors.nju.edu.cn/centos-cloud/",
      "size": "2.32T"
    },
    {
      "cname": "centos-stream",
      "desc": "",
      "url": "/centos-stream",
      "status": "S1675514323NX1675521523",
      "help": "",
      "upstream": "rsync://mirrors.tuna.tsinghua.edu.cn/centos-stream/",
      "size": "1.34T"
    },
    {
      "cname": "centos-vault",
      "desc": "为旧版本 CentOS 提供服务的软件包仓库",
      "url": "/centos-vault",
      "status": "S1675513193X1675520393",
      "help": "/help/centos-vault/",
      "upstream": "rsync://mirrors.tuna.tsinghua.edu.cn/centos-vault/",
      "size": "6.03T"
    },
    {
      "cname": "ceph",
      "desc": "高性能对象存储和文件系统",
      "url": "/ceph",
      "status": "S1675503462X1675517862",
      "help": "/help/ceph/",
      "upstream": "rsync://download.ceph.com/ceph/",
      "size": "2.48T"
    },
    {
      "cname": "chef",
      "desc": "自动化服务器配置管理工具",
      "url": "/chef",
      "status": "S1675514595X1675521795",
      "help": "/help/chef/",
      "upstream": "rsync://mirrors.tuna.tsinghua.edu.cn/chef/",
      "size": "435.94G"
    },
    {
      "cname": "clojars",
      "desc": "Clojure 语言的第三方软件包仓库",
      "url": "/clojars",
      "status": "S1675510757X1675517957",
      "help": "",
      "upstream": "rsync://mirrors.tuna.tsinghua.edu.cn/clojars/",
      "size": "95.72G"
    },
    {
      "cname": "cmder",
      "desc": "Windows 下的终端模拟器套件",
      "url": "/github-release/cmderdev/cmder",
      "status": "S1675509395X1675552595",
      "help": "",
      "upstream": "https://api.github.com/repos/"
    },
    {
      "cname": "CPAN",
      "desc": "Perl 语言软件库",
      "url": "/CPAN",
      "status": "S1675513110X1675527510",
      "help": "/help/CPAN/",
      "upstream": "rsync://cpan-rsync.perl.org/CPAN/",
      "size": "30.08G"
    },
    {
      "cname": "CRAN",
      "desc": "R 语言的可执行文件、源代码和说明文件，也收录了各种用户撰写的软件包",
      "url": "/CRAN",
      "status": "Y1675515125O1675507920",
      "help": "/help/CRAN/",
      "upstream": "rsync://mirrors.tuna.tsinghua.edu.cn/CRAN/",
      "size": "434.60G"
    },
    {
      "cname": "CTAN",
      "desc": "TeX 的各种发行版、软件包和文档",
      "url": "/CTAN",
      "status": "S1675506400X1675520800",
      "help": "/help/CTAN/",
      "upstream": "rsync://rsync.dante.ctan.org/CTAN/",
      "size": "52.87G"
    },
    {
      "cname": "ctex",
      "desc": "旧版 CTEX 安装镜像存档",
      "url": "/ctex",
      "status": "S1675514351X1675521551",
      "help": "",
      "upstream": "rsync://mirrors.tuna.tsinghua.edu.cn/ctex/",
      "size": "4.35G"
    },
    {
      "cname": "cygwin",
      "desc": "Cygwin 官方软件包仓库",
      "url": "/cygwin",
      "status": "S1675515332X1675529732",
      "help": "/help/cygwin/",
      "upstream": "rsync://mirrors.kernel.org/sourceware/cygwin/",
      "size": "107.71G"
    },
    {
      "cname": "dart-pub",
      "desc": "Dart 语言的软件包仓库",
      "url": "/dart-pub",
      "status": "S1675513285X1675520485",
      "help": "/help/dart-pub/",
      "upstream": "rsync://mirrors.tuna.tsinghua.edu.cn/dart-pub/",
      "size": "509.84G"
    },
    {
      "cname": "debian",
      "desc": "Debian Linux 的官方软件包仓库",
      "url": "/debian",
      "status": "S1675516489X1675518289",
      "help": "/help/debian/",
      "upstream": "rsync://mirrors.tuna.tsinghua.edu.cn/debian/",
      "size": "1.9T"
    },
    {
      "cname": "debian-archive",
      "desc": "",
      "url": "/debian-archive",
      "status": "S1675515778X1675517578",
      "help": "",
      "upstream": "rsync://archive.debian.org/debian-archive/",
      "size": "1.4T"
    },
    {
      "cname": "debian-cd",
      "desc": "Debian Linux 的安装镜像",
      "url": "/debian-cd",
      "status": "S1675512933X1675527333",
      "help": "",
      "upstream": "rsync://mirrors.kernel.org/debian-cd/",
      "size": "228.15G"
    },
    {
      "cname": "debian-nonfree",
      "desc": "Debian Linux 的非自由软件包仓库",
      "url": "/debian-nonfree",
      "status": "S1675504102X1675518502",
      "help": "",
      "upstream": "rsync://cdimage.debian.org/cdimage-unofficial/non-free/",
      "size": "4.95T"
    },
    {
      "cname": "debian-ports",
      "desc": "",
      "url": "/debian-ports",
      "status": "Y1675516879O1675515076",
      "help": "",
      "upstream": "rsync://ftp.de.debian.org/debian-ports/",
      "size": "1.2T"
    },
    {
      "cname": "debian-security",
      "desc": "Debian Linux 的安全更新",
      "url": "/debian-security",
      "status": "S1675515777X1675517577",
      "help": "",
      "upstream": "rsync://rsync.security.debian.org/debian-security/",
      "size": "289G"
    },
    {
      "cname": "debiancn",
      "desc": "",
      "url": "/debiancn",
      "status": "S1675512861X1675527261",
      "help": "",
      "upstream": "rsync://repo.debiancn.org/debiancn/",
      "size": "31.99G"
    },
    {
      "cname": "deepin",
      "desc": "Deepin Linux 的官方软件包仓库",
      "url": "/deepin",
      "status": "S1675515527X1675529927",
      "help": "",
      "upstream": "rsync://rsync.deepin.com/deepin/",
      "size": "394.84G"
    },
    {
      "cname": "deepin-cd",
      "desc": "Deepin Linux 的安装镜像",
      "url": "/deepin-cd",
      "status": "S1675512615X1675527015",
      "help": "",
      "upstream": "rsync://rsync.deepin.com/releases/",
      "size": "59.50G"
    },
    {
      "cname": "deepin-riscv",
      "desc": "",
      "url": "/deepin-riscv",
      "status": "S1675516865X1675518665",
      "help": "",
      "upstream": "rsync://rsync_deepin_riscv@192.168.16.13/deepin-riscv/",
      "size": "116.31G"
    },
    {
      "cname": "dell",
      "desc": "Dell 服务器管理工具",
      "url": "/dell",
      "status": "S1675508267X1675522667",
      "help": "",
      "upstream": "rsync://linux.dell.com/repo/",
      "size": "3.19T"
    },
    {
      "cname": "docker-ce",
      "desc": "Docker Community Edition 的安装包",
      "url": "/docker-ce",
      "status": "S1675514112X1675521312",
      "help": "/help/docker-ce/",
      "upstream": "rsync://mirrors.tuna.tsinghua.edu.cn/docker-ce/",
      "size": "755.42G"
    },
    {
      "cname": "dotdeb",
      "desc": "用于 Debian 服务器的额外镜像源",
      "url": "/dotdeb",
      "status": "S1675513040X1675527440",
      "help": "",
      "upstream": "rsync://mirror.us.leaseweb.net/dotdeb/",
      "size": "25.22G"
    },
    {
      "cname": "eclipse",
      "desc": "著名的集成开发环境 Eclipse",
      "url": "/eclipse",
      "status": "S1675513232X1675527632",
      "help": "",
      "upstream": "rsync://rsync.osuosl.org/eclipse/",
      "size": "1.30T"
    },
    {
      "cname": "elasticstack",
      "desc": "ELK 系列数据分析工具，5.x 之后改名为 Elastic Stack",
      "url": "/elasticstack",
      "status": "S1675514609X1675521809",
      "help": "/help/elasticsearch/",
      "upstream": "rsync://mirrors.tuna.tsinghua.edu.cn/elasticstack/",
      "size": "352.28G"
    },
    {
      "cname": "elpa",
      "desc": "Emacs 内建包管理器 package.el 的软件源",
      "url": "/elpa",
      "status": "S1675514707X1675521907",
      "help": "/help/elpa/",
      "upstream": "rsync://mirrors.bfsu.edu.cn/elpa/",
      "size": "3.55G"
    },
    {
      "cname": "elrepo",
      "desc": "RHEL 及其变体的 RPM 软件包仓库",
      "url": "/elrepo",
      "status": "S1675516167X1675530567",
      "help": "/help/elrepo/",
      "upstream": "rsync://ftp.yz.yamagata-u.ac.jp/pub/linux/RPMS/elrepo/",
      "size": "72.26G"
    },
    {
      "cname": "elvish",
      "desc": "TUNA 前会长 xiaq 开发的革命性 Shell",
      "url": "/elvish",
      "status": "S1675512899X1675527299",
      "help": "",
      "upstream": "rsync://rsync.elv.sh/elvish/",
      "size": "1.99G"
    },
    {
      "cname": "endeavouros",
      "desc": "",
      "url": "/endeavouros",
      "status": "S1675514185X1675528585",
      "help": "",
      "upstream": "rsync://mirror.alpix.eu/endeavouros/",
      "size": "44.12G"
    },
    {
      "cname": "epel",
      "desc": "企业版 Linux 附加软件包",
      "url": "/epel",
      "status": "S1675506949X1675521349",
      "help": "/help/epel/",
      "upstream": "rsync://fedora-rsync.ftp.pub.2iij.net/fedora-epel/",
      "size": "479.93G"
    },
    {
      "cname": "erlang-solutions",
      "desc": "为各大 Linux 发行版提供的 Erlang 软件包",
      "url": "/erlang-solutions",
      "status": "S1675514590X1675521790",
      "help": "/help/erlang-solutions/",
      "upstream": "rsync://mirrors.tuna.tsinghua.edu.cn/erlang-solutions/",
      "size": "35.99G"
    },
    {
      "cname": "eulixos",
      "desc": "",
      "url": "/eulixos",
      "status": "S1675514426X1675528826",
      "help": "",
      "upstream": "rsync://192.168.8.1/eulixos/",
      "size": "2.03T"
    },
    {
      "cname": "fdroid",
      "desc": "F-Droid 是 Android 上的自由与开源软件应用商店",
      "url": "/fdroid",
      "status": "S1675504653X1675519053",
      "help": "/help/fdroid/",
      "upstream": "rsync://ftp.lysator.liu.se/pub/fdroid/",
      "size": "1.25T"
    },
    {
      "cname": "fedora",
      "desc": "Fedora Linux 的安装镜像和官方软件包仓库",
      "url": "/fedora",
      "status": "Y1675372584O1675358182",
      "help": "/help/fedora/",
      "upstream": "rsync://download-ib01.fedoraproject.org/fedora-enchilada/linux/",
      "size": "5.62T"
    },
    {
      "cname": "fedora-altarch",
      "desc": "Fedora Linux 额外平台的安装镜像和官方软件包仓库",
      "url": "/fedora-altarch",
      "status": "S1675506818X1675521218",
      "help": "",
      "upstream": "rsync://download-ib01.fedoraproject.org/fedora-secondary/",
      "size": "3.47T"
    },
    {
      "cname": "fedora.riscv.rocks",
      "desc": "",
      "url": "/fedora.riscv.rocks",
      "status": "S1675504802X1675519202",
      "help": "",
      "upstream": "http://fedora.riscv.rocks/repos-dist/rawhide/latest/",
      "size": "157G"
    },
    {
      "cname": "flightgear",
      "desc": "多平台的飞行模拟器",
      "url": "/flightgear",
      "status": "S1675513106X1675527506",
      "help": "",
      "upstream": "rsync://mirrors.ibiblio.org/flightgear/",
      "size": "323.74G"
    },
    {
      "cname": "flutter",
      "desc": "Flutter 框架 SDK 镜像",
      "url": "/flutter",
      "status": "S1675513923X1675521123",
      "help": "/help/flutter/",
      "upstream": "rsync://mirrors.tuna.tsinghua.edu.cn/flutter/",
      "size": "1.98T"
    },
    {
      "cname": "FreeBSD",
      "desc": "",
      "url": "/FreeBSD",
      "status": "S1675511499X1675525899",
      "help": "",
      "upstream": "rsync://ftp.tw.freebsd.org/FreeBSD/",
      "size": "1.19T"
    },
    {
      "cname": "FreeCAD",
      "desc": "基于 Qt 的计算机辅助设计程序",
      "url": "/github-release/FreeCAD/FreeCAD",
      "status": "S1675509395X1675552595",
      "help": "",
      "upstream": "https://api.github.com/repos/"
    },
    {
      "cname": "fzug",
      "desc": "Fedora 中文用户组的软件包仓库",
      "url": "/fzug",
      "status": "S1675512120X1675519320",
      "help": "",
      "upstream": "rsync://mirrors.bfsu.edu.cn/fzug/",
      "size": "9.81G"
    },
    {
      "cname": "garuda-linux",
      "desc": "Garuda Linux是基于Arch Linux操作系统的滚动式发行版",
      "url": "/osdn/storage/g/g/ga/garuda-linux",
      "status": "S1675514871X1675522071",
      "help": "",
      "upstream": "rsync://mirrors.bfsu.edu.cn/osdn/"
    },
    {
      "cname": "gentoo",
      "desc": "Gentoo Linux 的 Stage 3 镜像",
      "url": "/gentoo",
      "status": "Y1675510479O1675496078",
      "help": "",
      "upstream": "rsync://mirror.us.leaseweb.net/gentoo/",
      "size": "623.68G"
    },
    {
      "cname": "gentoo-portage",
      "desc": "Gentoo Linux 的 Portage 包管理器镜像源（HTTP / rsync 访问）",
      "url": "/gentoo-portage",
      "status": "S1675502848X1675517248",
      "help": "/help/gentoo-portage/",
      "upstream": "rsync://rsync.jp.gentoo.org/gentoo-portage/",
      "size": "184.26M"
    },
    {
      "cname": "gentoo-portage-prefix",
      "desc": "Gentoo/Prefix 的 Portage 包管理器镜像源（仅适用于 macOS）",
      "url": "/gentoo-portage-prefix",
      "status": "S1675502963X1675517363",
      "help": "/help/gentoo-prefix/",
      "upstream": "rsync://rsync.prefix.bitzolder.nl/gentoo-portage-prefix/",
      "size": "185.25M"
    },
    {
      "cname": "git-for-windows",
      "desc": "Git 工具的 Windows 系统版本",
      "url": "/github-release/git-for-windows/git",
      "status": "S1675509395X1675552595",
      "help": "",
      "upstream": "https://api.github.com/repos/"
    },
    {
      "cname": "github-release",
      "desc": "一些项目的 Github Release 镜像",
      "url": "/github-release",
      "status": "S1675509395X1675552595",
      "help": "",
      "upstream": "https://api.github.com/repos/",
      "size": "96.23G"
    },
    {
      "cname": "gitlab-ce",
      "desc": "Gitlab 社区版",
      "url": "/gitlab-ce",
      "status": "S1675513580X1675527980",
      "help": "/help/gitlab-ce/",
      "upstream": "rsync://mirrors.tuna.tsinghua.edu.cn/gitlab-ce/",
      "size": "1.56T"
    },
    {
      "cname": "gitlab-ee",
      "desc": "Gitlab 企业版",
      "url": "/gitlab-ee",
      "status": "S1675513435X1675527835",
      "help": "",
      "upstream": "rsync://mirrors.tuna.tsinghua.edu.cn/gitlab-ee/",
      "size": "1.70T"
    },
    {
      "cname": "gitlab-runner",
      "desc": "GitLab 持续集成框架版本 10 及以上",
      "url": "/gitlab-runner",
      "status": "S1675514275X1675521475",
      "help": "/help/gitlab-runner/",
      "upstream": "rsync://mirrors.tuna.tsinghua.edu.cn/gitlab-runner/",
      "size": "529.48G"
    },
    {
      "cname": "gmt",
      "desc": "",
      "url": "/gmt",
      "status": "S1675513711X1675528111",
      "help": "",
      "upstream": "rsync://gmt.mirror.ac.za/gmt/",
      "size": "150.65G"
    },
    {
      "cname": "gnu",
      "desc": "GNU 项目的软件包（源代码、文档和部分平台的二进制文件）",
      "url": "/gnu",
      "status": "S1675513649X1675528049",
      "help": "",
      "upstream": "rsync://ftp.gnu.org/gnu/",
      "size": "151.74G"
    },
    {
      "cname": "gnu-alpha",
      "desc": "一些尚未达到生产质量的 GNU 项目的软件包",
      "url": "/gnu-alpha",
      "status": "S1675513057X1675527457",
      "help": "",
      "upstream": "rsync://ftp.gnu.org/alpha/",
      "size": "82.12G"
    },
    {
      "cname": "googlefonts",
      "desc": "Google 设计的 Noto 系列开源字体",
      "url": "/github-release/googlefonts",
      "status": "S1675509395X1675552595",
      "help": "",
      "upstream": "https://api.github.com/repos/"
    },
    {
      "cname": "grafana",
      "desc": "开源的数据可视化工具",
      "url": "/grafana",
      "status": "S1675514608X1675521808",
      "help": "/help/grafana/",
      "upstream": "rsync://mirrors.tuna.tsinghua.edu.cn/grafana/",
      "size": "110.73G"
    },
    {
      "cname": "hackage",
      "desc": "Haskell 社区的中心软件包仓库",
      "url": "/hackage",
      "status": "S1675508368X1675515568",
      "help": "/help/hackage/",
      "upstream": "rsync://mirrors.tuna.tsinghua.edu.cn/hackage/",
      "size": "15.83G"
    },
    {
      "cname": "harmonyos",
      "desc": "",
      "url": "/harmonyos",
      "status": "S1675512090X1675526490",
      "help": "",
      "upstream": "https://repo.huaweicloud.com/harmonyos/",
      "size": "488G"
    },
    {
      "cname": "hbcd",
      "desc": "",
      "url": "/hbcd",
      "status": "S1675512941X1675527341",
      "help": "",
      "upstream": "rsync://rsync.hirensbootcd.org/mirror/",
      "size": "4.19G"
    },
    {
      "cname": "homebrew-bottles",
      "desc": "预编译的 Homebrew 软件包",
      "url": "/homebrew-bottles",
      "status": "S1675508282X1675515482",
      "help": "/help/homebrew-bottles/",
      "upstream": "rsync://mirrors.tuna.tsinghua.edu.cn/homebrew-bottles/",
      "size": "476.48G"
    },
    {
      "cname": "iina",
      "desc": "macOS 上的现代化开源视频播放器",
      "url": "/iina",
      "status": "S1675512699X1675527099",
      "help": "",
      "upstream": "rsync://link-start.iina.io/iina/",
      "size": "1.89G"
    },
    {
      "cname": "iina",
      "desc": "macOS 上的现代化开源视频播放器",
      "url": "/github-release/iina/iina",
      "status": "S1675509395X1675552595",
      "help": "",
      "upstream": "https://api.github.com/repos/"
    },
    {
      "cname": "influxdata",
      "desc": "时间序列数据平台",
      "url": "/influxdata",
      "status": "S1675514385X1675521585",
      "help": "/help/influxdata/",
      "upstream": "rsync://mirrors.tuna.tsinghua.edu.cn/influxdata/",
      "size": "13.49G"
    },
    {
      "cname": "ius",
      "desc": "为企业版 Linux 提供最新软件包的镜像源",
      "url": "/ius",
      "status": "S1675513014X1675527414",
      "help": "",
      "upstream": "rsync://origin.repo.ius.io/ius/",
      "size": "36.76G"
    },
    {
      "cname": "jenkins",
      "desc": "用 Java 编写的持续集成框架",
      "url": "/jenkins",
      "status": "S1675504015X1675518415",
      "help": "",
      "upstream": "rsync://rsync.osuosl.org/jenkins/",
      "size": "157.78G"
    },
    {
      "cname": "julia",
      "desc": "Julia 编程语言的包管理器镜像",
      "url": "/julia",
      "status": "S1675513745X1675520945",
      "help": "/help/julia/",
      "upstream": "rsync://mirrors.bfsu.edu.cn/julia/",
      "size": "3.73T"
    },
    {
      "cname": "julia-releases",
      "desc": "Julia 二进制程序镜像",
      "url": "/julia-releases",
      "status": "S1675514581X1675521781",
      "help": "/help/julia-releases/",
      "upstream": "rsync://mirrors.tuna.tsinghua.edu.cn/julia-releases/",
      "size": "143.35G"
    },
    {
      "cname": "kali",
      "desc": "Kali Linux 的官方软件包仓库",
      "url": "/kali",
      "status": "S1675508322X1675522722",
      "help": "/help/kali/",
      "upstream": "rsync://ftp.nluug.nl/kali/",
      "size": "747.39G"
    },
    {
      "cname": "kali-images",
      "desc": "Kali Linux 的安装镜像",
      "url": "/kali-images",
      "status": "S1675513484X1675527884",
      "help": "",
      "upstream": "rsync://ftp.nluug.nl/kali-images/",
      "size": "140.98G"
    },
    {
      "cname": "KaOS",
      "desc": "一个基于 KDE 的独立发行版",
      "url": "/KaOS",
      "status": "Y1675512009O1675497605",
      "help": "",
      "upstream": "rsync://kaosx.tk/kaos/",
      "size": "16.82G"
    },
    {
      "cname": "kde",
      "desc": "KDE主源码镜像",
      "url": "/kde",
      "status": "S1675506792X1675521192",
      "help": "",
      "upstream": "rsync://rsync.kde.org/kdeftp/",
      "size": "775.73G"
    },
    {
      "cname": "kde-neon",
      "desc": "KDE社区维护的一个基于Ubuntu LTS的Linux发行版",
      "url": "/kde-neon",
      "status": "S1675511789X1675518989",
      "help": "",
      "upstream": "rsync://mirrors.bfsu.edu.cn/kde-neon/",
      "size": "415.91G"
    },
    {
      "cname": "kernel",
      "desc": "各个版本的 Linux 内核源代码压缩包和补丁",
      "url": "/kernel",
      "status": "S1675508484X1675522884",
      "help": "",
      "upstream": "rsync://rsync.kernel.org/pub/linux/kernel/",
      "size": "981.98G"
    },
    {
      "cname": "kernel.org",
      "desc": "",
      "url": "/kernel.org",
      "status": "S1675516282X1675530682",
      "help": "",
      "upstream": "rsync://rsync.kernel.org/pub/",
      "size": "1.13T"
    },
    {
      "cname": "kicad",
      "desc": "开源的电路原理图与 PCB 设计工具",
      "url": "/kicad",
      "status": "S1675509040X1675516240",
      "help": "/help/kicad/",
      "upstream": "rsync://mirrors.tuna.tsinghua.edu.cn/kicad/",
      "size": "207.45G"
    },
    {
      "cname": "knoppix",
      "desc": "",
      "url": "/knoppix",
      "status": "S1675512932X1675527332",
      "help": "",
      "upstream": "rsync://ftp.uni-kl.de/knoppix/",
      "size": "7.35G"
    },
    {
      "cname": "kodi",
      "desc": "开源的多媒体播放器，原名 XBMC",
      "url": "/kodi",
      "status": "S1675516647X1675531047",
      "help": "",
      "upstream": "rsync://mirror.yandex.ru/mirrors/xbmc/",
      "size": "251.28G"
    },
    {
      "cname": "kubernetes",
      "desc": "Kubernetes 是用于集群自动部署和管理的开源系统",
      "url": "/kubernetes",
      "status": "S1675514565X1675521765",
      "help": "/help/kubernetes/",
      "upstream": "rsync://mirrors.tuna.tsinghua.edu.cn/kubernetes/",
      "size": "71.01G"
    },
    {
      "cname": "kunpeng",
      "desc": "",
      "url": "/kunpeng",
      "status": "S1675508267X1675522667",
      "help": "",
      "upstream": "https://repo.huaweicloud.com/kunpeng/",
      "size": "177G"
    },
    {
      "cname": "lfs",
      "desc": "",
      "url": "/lfs",
      "status": "S1675512943X1675527343",
      "help": "",
      "upstream": "rsync://ftp.osuosl.org/lfs/",
      "size": "31.68G"
    },
    {
      "cname": "lfs-livecd",
      "desc": "",
      "url": "/lfs-livecd",
      "status": "S1675512845X1675527245",
      "help": "",
      "upstream": "rsync://ftp.osuosl.org/lfs-livecd/",
      "size": "11.44G"
    },
    {
      "cname": "libreoffice",
      "desc": "自由的办公软件套件",
      "url": "/libreoffice",
      "status": "S1675513820X1675528220",
      "help": "",
      "upstream": "rsync://rsync.documentfoundation.org/tdf-pub/",
      "size": "100.81G"
    },
    {
      "cname": "lineage-rom",
      "desc": "最大的社区Android发行版之一Lineage的ROM",
      "url": "/lineage-rom",
      "status": "S1675511476X1675518676",
      "help": "/help/lineage-rom/",
      "upstream": "rsync://mirrors.bfsu.edu.cn/lineage-rom/",
      "size": "918.54G"
    },
    {
      "cname": "linuxlite-cd",
      "desc": "基于 Ubuntu 长期支持版本（LTS）的 Linux 发行版 Linux Lite 的安装镜像",
      "url": "/osdn/storage/g/l/li/linuxlite",
      "status": "S1675514871X1675522071",
      "help": "",
      "upstream": "rsync://mirrors.bfsu.edu.cn/osdn/"
    },
    {
      "cname": "linuxmint",
      "desc": "Linux Mint 的官方软件源",
      "url": "/linuxmint",
      "status": "S1675513392X1675527792",
      "help": "/help/linuxmint/",
      "upstream": "rsync://rsync-packages.linuxmint.com/packages/",
      "size": "38.53G"
    },
    {
      "cname": "linuxmint-cd",
      "desc": "Linux Mint 的安装镜像",
      "url": "/linuxmint-cd",
      "status": "S1675512915X1675527315",
      "help": "",
      "upstream": "rsync://pub.linuxmint.com/pub/",
      "size": "387.85G"
    },
    {
      "cname": "llvm-apt",
      "desc": "LLVM 编译器套件的 APT 安装源",
      "url": "/llvm-apt",
      "status": "S1675514110X1675521310",
      "help": "/help/llvm-apt/",
      "upstream": "rsync://mirrors.tuna.tsinghua.edu.cn/llvm-apt/",
      "size": "13.08G"
    },
    {
      "cname": "llvm-binary",
      "desc": "LLVM 编译器套件可执行文件",
      "url": "/github-release/llvm/llvm-project",
      "status": "S1675509395X1675552595",
      "help": "",
      "upstream": "https://api.github.com/repos/"
    },
    {
      "cname": "loongarch",
      "desc": "",
      "url": "/loongarch",
      "status": "S1675516213X1675518013",
      "help": "",
      "upstream": "rsync://mirrors.wsyu.edu.cn/loongarch/",
      "size": "99.17G"
    },
    {
      "cname": "loongson",
      "desc": "用于龙芯电脑的软件包",
      "url": "/loongson",
      "status": "S1675512650X1675527050",
      "help": "",
      "upstream": "rsync://rsync.anheng.com.cn/loongson/",
      "size": "20.29G"
    },
    {
      "cname": "lxc-images",
      "desc": "Linux 容器的镜像",
      "url": "/lxc-images",
      "status": "Y1675510395O1675503194",
      "help": "/help/lxc-images/",
      "upstream": "rsync://mirrors.tuna.tsinghua.edu.cn/lxc-images/",
      "size": "470.28G"
    },
    {
      "cname": "lyx",
      "desc": "所见即所指的 LaTeX 编辑器",
      "url": "/lyx",
      "status": "S1675514390X1675521590",
      "help": "",
      "upstream": "rsync://mirrors.tuna.tsinghua.edu.cn/lyx/",
      "size": "28.26G"
    },
    {
      "cname": "macports",
      "desc": "macOS 的一个开源软件包管理系统",
      "url": "/macports",
      "status": "S1675513668X1675528068",
      "help": "",
      "upstream": "rsync://rsync-origin.macports.org/macports/",
      "size": "2.32T"
    },
    {
      "cname": "mageia",
      "desc": "Mageia Linux（衍生于 Mandriva Linux）的安装镜像和官方软件包仓库",
      "url": "/mageia",
      "status": "Y1675502094O1675487691",
      "help": "",
      "upstream": "rsync://mirrors.kernel.org/mageia/",
      "size": "2.79T"
    },
    {
      "cname": "manjaro",
      "desc": "Manjaro Linux 的官方软件源",
      "url": "/manjaro",
      "status": "Y1675510359O1675495958",
      "help": "",
      "upstream": "rsync://mirror.yandex.ru/mirrors/manjaro/",
      "size": "130.86G"
    },
    {
      "cname": "manjaro-arm",
      "desc": "Manjaro ARM Linux 的官方软件源",
      "url": "/manjaro-arm",
      "status": "S1675516879X1675531279",
      "help": "",
      "upstream": "rsync://ftp.osuosl.org/manjaro-arm/repo/",
      "size": "22.11G"
    },
    {
      "cname": "mariadb",
      "desc": "衍生于 MySQL 的开源关系数据库",
      "url": "/mariadb",
      "status": "Y1675468924O1675368997",
      "help": "/help/mariadb/",
      "upstream": "rsync://rsync.osuosl.org/mariadb/",
      "size": "868.73G"
    },
    {
      "cname": "miniforge",
      "desc": "适用于 conda-forge 的最小化 conda 安装器",
      "url": "/github-release/conda-forge/miniforge",
      "status": "S1675509395X1675552595",
      "help": "",
      "upstream": "https://api.github.com/repos/"
    },
    {
      "cname": "minikube",
      "desc": "在本地运行的单节点 Kubernetes 集群安装工具",
      "url": "/github-release/kubernetes/minikube",
      "status": "S1675509395X1675552595",
      "help": "",
      "upstream": "https://api.github.com/repos/"
    },
    {
      "cname": "mongodb",
      "desc": "开源的跨平台 NoSQL 文档型数据库",
      "url": "/mongodb",
      "status": "S1675513450X1675520650",
      "help": "/help/mongodb/",
      "upstream": "rsync://mirrors.bfsu.edu.cn/mongodb/",
      "size": "74.70G"
    },
    {
      "cname": "msys2",
      "desc": "用于编译原生 Windows 程序的类 Linux 开发环境",
      "url": "/msys2",
      "status": "S1675508446X1675515646",
      "help": "/help/msys2/",
      "upstream": "rsync://mirrors.tuna.tsinghua.edu.cn/msys2/",
      "size": "704.95G"
    },
    {
      "cname": "mxlinux-isos",
      "desc": "MX Linux 的安装镜像",
      "url": "/osdn/storage/g/m/mx/mx-linux/ISOs",
      "status": "S1675514871X1675522071",
      "help": "",
      "upstream": "rsync://mirrors.bfsu.edu.cn/osdn/"
    },
    {
      "cname": "mysql",
      "desc": "MySQL 数据库的安装包及各种工具下载",
      "url": "/mysql",
      "status": "S1675514652X1675521852",
      "help": "/help/mysql/",
      "upstream": "rsync://mirrors.tuna.tsinghua.edu.cn/mysql/",
      "size": "733.93G"
    },
    {
      "cname": "NetBSD",
      "desc": "NetBSD 的安装镜像和部分系统源码",
      "url": "/NetBSD",
      "status": "Y1675495044O1675480640",
      "help": "/help/netbsd/",
      "upstream": "rsync://rsync.NetBSD.org/NetBSD/",
      "size": "843.93G"
    },
    {
      "cname": "neurodebian",
      "desc": "用于神经科学研究的 Debian 软件包源",
      "url": "/neurodebian",
      "status": "S1675513004X1675527404",
      "help": "",
      "upstream": "rsync://neuro.debian.net/neurodebian/",
      "size": "78.99G"
    },
    {
      "cname": "nix",
      "desc": "Nix 软件包管理器",
      "url": "/nix",
      "status": "S1675514576X1675521776",
      "help": "/help/nix/",
      "upstream": "rsync://mirrors.tuna.tsinghua.edu.cn/nix/",
      "size": "11.73G"
    },
    {
      "cname": "nix-channels",
      "desc": "Nixpkgs 软件包发行版",
      "url": "/nix-channels",
      "status": "Y1675365136O1675305133",
      "help": "",
      "upstream": "https://nixos.org/channels",
      "size": "unknown"
    },
    {
      "cname": "nixos-images",
      "desc": "NixOS 的安装镜像和虚拟机镜像",
      "url": "/nixos-images",
      "status": "S1675514740X1675521940",
      "help": "",
      "upstream": "rsync://mirrors.tuna.tsinghua.edu.cn/nixos-images/",
      "size": "52.45G"
    },
    {
      "cname": "nodejs-release",
      "desc": "预编译的 Node.js 二进制程序",
      "url": "/nodejs-release",
      "status": "S1675511111X1675525511",
      "help": "/help/nodejs-release/",
      "upstream": "rsync://unencrypted.nodejs.org/nodejs/release/",
      "size": "337.46G"
    },
    {
      "cname": "obs-studio",
      "desc": "自由的流媒体与视频录制程序（Open Broadcast Software）",
      "url": "/github-release/obsproject/obs-studio",
      "status": "S1675509395X1675552595",
      "help": "",
      "upstream": "https://api.github.com/repos/"
    },
    {
      "cname": "OpenBSD",
      "desc": "OpenBSD 的安装镜像和官方软件包仓库",
      "url": "/OpenBSD",
      "status": "S1675502555X1675516955",
      "help": "/help/openbsd/",
      "upstream": "rsync://mirror.aarnet.edu.au/openbsd/",
      "size": "1.09T"
    },
    {
      "cname": "openembedded",
      "desc": "",
      "url": "/openembedded",
      "status": "Y1675510726O1675496323",
      "help": "",
      "upstream": "http://sources.openembedded.org/",
      "size": "113G"
    },
    {
      "cname": "openeuler",
      "desc": "华为公司开源的服务器操作系统",
      "url": "/openeuler",
      "status": "S1675507880X1675522280",
      "help": "",
      "upstream": "rsync://121.36.97.194/openeuler/",
      "size": "2.90T"
    },
    {
      "cname": "OpenMediaVault",
      "desc": "基于 Debian Linux 的网络附加存储(NAS)解决方案",
      "url": "/OpenMediaVault",
      "status": "S1675514380X1675521580",
      "help": "/help/openmediavault/",
      "upstream": "rsync://mirrors.tuna.tsinghua.edu.cn/OpenMediaVault/",
      "size": "92.45M"
    },
    {
      "cname": "openresty",
      "desc": "基于 Nginx 与 Lua 的高性能 Web 平台",
      "url": "/openresty",
      "status": "S1675514571X1675521771",
      "help": "",
      "upstream": "rsync://mirrors.tuna.tsinghua.edu.cn/openresty/",
      "size": "55.21G"
    },
    {
      "cname": "opensuse",
      "desc": "openSUSE 的安装镜像和官方软件包仓库",
      "url": "/opensuse",
      "status": "Y1675479157O1675471954",
      "help": "/help/opensuse/",
      "upstream": "rsync://mirrors.nju.edu.cn/opensuse/",
      "size": "7.61T"
    },
    {
      "cname": "openvz",
      "desc": "",
      "url": "/openvz",
      "status": "S1675516318X1675530718",
      "help": "",
      "upstream": "rsync://download.openvz.org/openvz-download/",
      "size": "385.78G"
    },
    {
      "cname": "openwrt",
      "desc": "OpenWrt/LEDE 软件包镜像源",
      "url": "/openwrt",
      "status": "Y1675464379O1675357138",
      "help": "/help/openwrt/",
      "upstream": "rsync://downloads.openwrt.org/downloads/",
      "size": "1.99T"
    },
    {
      "cname": "opnsense",
      "desc": "OPNsense 是基于 FreeBSD 的防火墙和路由软件",
      "url": "/opnsense",
      "status": "S1675505130X1675519530",
      "help": "",
      "upstream": "rsync://rsync.opnsense.org/opnsense-dist/",
      "size": "126.07G"
    },
    {
      "cname": "orchestrator",
      "desc": "MySQL 高可用与复制管理工具",
      "url": "/github-release/openark/orchestrator",
      "status": "S1675509395X1675552595",
      "help": "",
      "upstream": "https://api.github.com/repos/"
    },
    {
      "cname": "osdn",
      "desc": "OSDN 网站提供的开源软件下载",
      "url": "/osdn",
      "status": "S1675514871X1675522071",
      "help": "",
      "upstream": "rsync://mirrors.bfsu.edu.cn/osdn/",
      "size": "368.94G"
    },
    {
      "cname": "osmc",
      "desc": "免费、开源的媒体中心解决方案",
      "url": "/osmc",
      "status": "S1675509682X1675524082",
      "help": "",
      "upstream": "rsync://rsync.samnazarko.co.uk/cdn/",
      "size": "129.28G"
    },
    {
      "cname": "ovirt",
      "desc": "",
      "url": "/ovirt",
      "status": "S1675513835X1675528235",
      "help": "",
      "upstream": "rsync://ftp.plusline.net/ovirt/",
      "size": "1.14T"
    },
    {
      "cname": "packman",
      "desc": "为 Debian、Fedora、openSUSE、Ubuntu 提供额外和过期软件包的仓库",
      "url": "/packman",
      "status": "S1675515000X1675529400",
      "help": "",
      "upstream": "rsync://mirror.karneval.cz/packman/",
      "size": "160.61G"
    },
    {
      "cname": "parrot",
      "desc": "Parrot Linux（专注于安全审计的 Linux 发行版）的安装映像和官方软件源",
      "url": "/parrot",
      "status": "S1675505922X1675520322",
      "help": "",
      "upstream": "rsync://archive.parrotsec.org/parrot/",
      "size": "432.97G"
    },
    {
      "cname": "percona",
      "desc": "开源的数据库解决方案，详见 http://www.percona.com",
      "url": "/percona",
      "status": "S1675514663X1675529063",
      "help": "",
      "upstream": "rsync://rsync.percona.com/rsync/",
      "size": "4.46T"
    },
    {
      "cname": "pkgsrc",
      "desc": "NetBSD 的第三方软件源",
      "url": "/pkgsrc",
      "status": "S1675511343X1675525743",
      "help": "/help/pkgsrc/",
      "upstream": "rsync://rsync3.jp.NetBSD.org/pub/pkgsrc/",
      "size": "2.94T"
    },
    {
      "cname": "postgresql",
      "desc": "著名的开源关系型数据库 PostgreSQL 的镜像",
      "url": "/postgresql",
      "status": "S1675506233X1675520633",
      "help": "",
      "upstream": "rsync://ftp.postgresql.org/pgsql-ftp/",
      "size": "395.94G"
    },
    {
      "cname": "postmarketOS",
      "desc": "",
      "url": "/postmarketOS",
      "status": "S1675513726X1675528126",
      "help": "/help/postmarketOS/",
      "upstream": "rsync://mirror.postmarketos.org/postmarketos/",
      "size": "23.64G"
    },
    {
      "cname": "postmarketOS-images",
      "desc": "",
      "url": "/postmarketOS-images",
      "status": "S1675515399X1675529799",
      "help": "",
      "upstream": "rsync://mirror.postmarketos.org/images/",
      "size": "837.40G"
    },
    {
      "cname": "prometheus",
      "desc": "一个系统与服务监控系统",
      "url": "/github-release/prometheus/prometheus",
      "status": "S1675509395X1675552595",
      "help": "",
      "upstream": "https://api.github.com/repos/"
    },
    {
      "cname": "proxmox",
      "desc": "服务器虚拟化环境 Linux 发行版 Proxmox VE",
      "url": "/proxmox",
      "status": "S1675510459X1675517659",
      "help": "/help/proxmox/",
      "upstream": "rsync://mirrors.bfsu.edu.cn/proxmox/",
      "size": "141.08G"
    },
    {
      "cname": "putty",
      "desc": "",
      "url": "/putty",
      "status": "S1675512977X1675527377",
      "help": "",
      "upstream": "rsync://rsync.chiark.greenend.org.uk/ftp/users/sgtatham/putty-website-mirror/",
      "size": "75.30M"
    },
    {
      "cname": "qt",
      "desc": "跨平台软件开发库 Qt 的源码、开发工具、文档等",
      "url": "/qt",
      "status": "Y1675492419O1675478015",
      "help": "/help/qt/",
      "upstream": "rsync://master.qt-project.org/qt-all/",
      "size": "2.10T"
    },
    {
      "cname": "qubesos",
      "desc": "一个面向安全的桌面操作系统，利用虚拟化技术隔离应用来提供安全保障",
      "url": "/qubesos",
      "status": "S1675515128X1675529528",
      "help": "/help/qubesos/",
      "upstream": "rsync://rsync.qubes-os.org/qubes-mirror/",
      "size": "452.87G"
    },
    {
      "cname": "racket-installers",
      "desc": "Racket 语言环境安装包",
      "url": "/racket-installers",
      "status": "S1675513134X1675527534",
      "help": "",
      "upstream": "rsync://mirror.csclub.uwaterloo.ca/racket/racket-installers/",
      "size": "76.43G"
    },
    {
      "cname": "raspberry-pi-os-images",
      "desc": "Raspberry Pi OS （原 Raspbian）的安装镜像",
      "url": "/raspberry-pi-os-images",
      "status": "S1675510840X1675518040",
      "help": "",
      "upstream": "rsync://mirrors.bfsu.edu.cn/raspberry-pi-os-images/",
      "size": "542.10G"
    },
    {
      "cname": "raspberrypi",
      "desc": "一些专为树莓派提供的 Debian 软件包",
      "url": "/raspberrypi",
      "status": "S1675511100X1675518300",
      "help": "",
      "upstream": "rsync://mirrors.bfsu.edu.cn/raspberrypi/",
      "size": "285.17G"
    },
    {
      "cname": "raspbian",
      "desc": "为树莓派编译的 Debian 系统软件源",
      "url": "/raspbian",
      "status": "S1675510018X1675517218",
      "help": "/help/raspbian/",
      "upstream": "rsync://mirrors.bfsu.edu.cn/raspbian/",
      "size": "590.89G"
    },
    {
      "cname": "realsense",
      "desc": "",
      "url": "/realsense",
      "status": "S1675514541X1675528941",
      "help": "",
      "upstream": "https://isrc.iscas.ac.cn/mirror/realsense/",
      "size": "25G"
    },
    {
      "cname": "remi",
      "desc": "包含最新版本 PHP 和 MySQL 的第三方 yum 源",
      "url": "/remi",
      "status": "S1675512656X1675527056",
      "help": "",
      "upstream": "rsync://rpms.remirepo.net/",
      "size": "unknown"
    },
    {
      "cname": "repo-ck",
      "desc": "repo-ck 是 Arch 的非官方仓库，内有包含 ck 补丁、BFS 调度器等",
      "url": "/repo-ck",
      "status": "S1675512544X1675519744",
      "help": "/help/repo-ck/",
      "upstream": "rsync://mirrors.bfsu.edu.cn/repo-ck/",
      "size": "801.19M"
    },
    {
      "cname": "riscv-toolchains",
      "desc": "",
      "url": "/riscv-toolchains",
      "status": "S1675516027X1675519627",
      "help": "",
      "upstream": "https://api.github.com/repos/",
      "size": "138.69G"
    },
    {
      "cname": "RobinOS",
      "desc": "",
      "url": "/RobinOS",
      "status": "S1675516212X1675517112",
      "help": "",
      "upstream": "rsync://repo.tarsier-infra.com/RobinOS-RISC-V/",
      "size": "29.22G"
    },
    {
      "cname": "rocky",
      "desc": "",
      "url": "/rocky",
      "status": "S1675516426X1675530826",
      "help": "",
      "upstream": "rsync://msync.rockylinux.org/rocky/mirror/pub/rocky/",
      "size": "1.08T"
    },
    {
      "cname": "ros",
      "desc": "ROS 提供一系列程序库和工具以帮助软件开发者创建机器人应用软件",
      "url": "/ros",
      "status": "S1675515301X1675529701",
      "help": "/help/ros/",
      "upstream": "rsync://mirror.umd.edu/packages.ros.org/ros/",
      "size": "98.95G"
    },
    {
      "cname": "ros2",
      "desc": "ROS (Robot Operating System) 2.0 版本",
      "url": "/ros2",
      "status": "S1675509798X1675516998",
      "help": "/help/ros2/",
      "upstream": "rsync://mirrors.bfsu.edu.cn/ros2/",
      "size": "68.22G"
    },
    {
      "cname": "rpmfusion",
      "desc": "RPM Fusion 提供了一些 Fedora Project 和 Red Hat 不包含的软件",
      "url": "/rpmfusion",
      "status": "S1675510222X1675524622",
      "help": "/help/rpmfusion/",
      "upstream": "rsync://download1.rpmfusion.org/rpmfusion/",
      "size": "171.17G"
    },
    {
      "cname": "rudder",
      "desc": "自动化 IT 基础设施配置与审计工具",
      "url": "/rudder",
      "status": "S1675514370X1675521570",
      "help": "/help/rudder/",
      "upstream": "rsync://mirrors.tuna.tsinghua.edu.cn/rudder/",
      "size": "1.13G"
    },
    {
      "cname": "rust-analyzer",
      "desc": "Rust 语言的模块化编译器前端",
      "url": "/github-release/rust-analyzer/rust-analyzer",
      "status": "S1675509395X1675552595",
      "help": "",
      "upstream": "https://api.github.com/repos/"
    },
    {
      "cname": "rustup",
      "desc": "Rust 的官方安装工具",
      "url": "/rustup",
      "status": "S1675509882X1675517082",
      "help": "/help/rustup/",
      "upstream": "rsync://mirrors.tuna.tsinghua.edu.cn/rustup/",
      "size": "1.16T"
    },
    {
      "cname": "sagemath",
      "desc": "构建在 NumPy, SciPy 等工具之上的开源数学软件系统",
      "url": "/sagemath",
      "status": "S1675513014X1675527414",
      "help": "",
      "upstream": "rsync://files.sagemath.org/sage/",
      "size": "442.55G"
    },
    {
      "cname": "saltstack",
      "desc": "基于 python 的配置管理与运维自动化工具",
      "url": "/saltstack",
      "status": "S1675509973X1675517173",
      "help": "",
      "upstream": "rsync://mirrors.bfsu.edu.cn/saltstack/",
      "size": "119.13G"
    },
    {
      "cname": "sb",
      "desc": "",
      "url": "/sb",
      "status": "S1675512928X1675527328",
      "help": "",
      "upstream": "rsync://mirrors.xtom.com/repo/sb/",
      "size": "168.47M"
    },
    {
      "cname": "slackware",
      "desc": "Linux 发行版 Slackware 的源代码和官方软件包仓库",
      "url": "/slackware",
      "status": "S1675506329X1675520729",
      "help": "",
      "upstream": "rsync://ftp.slackware.com/slackware/",
      "size": "174.41G"
    },
    {
      "cname": "slackwarearm",
      "desc": "用于 ARM 设备的 Slackware 发行版源代码和官方软件包仓库",
      "url": "/slackwarearm",
      "status": "S1675504247X1675518647",
      "help": "",
      "upstream": "rsync://ftp.arm.slackware.com/slackwarearm/",
      "size": "44.72G"
    },
    {
      "cname": "solus",
      "desc": "Solus 的软件仓库，致力于制作对新手友好的发行版",
      "url": "/solus",
      "status": "S1675512226X1675526626",
      "help": "/help/solus/",
      "upstream": "rsync://mirrors.rit.edu/solus/",
      "size": "2.47T"
    },
    {
      "cname": "stackag",
      "desc": "",
      "url": "/stackag",
      "status": "S1675515301X1675522501",
      "help": "",
      "upstream": "rsync://mirrors.bfsu.edu.cn/stackage/",
      "size": "102.15G"
    },
    {
      "cname": "stellarium",
      "desc": "自由的模拟天文台软件",
      "url": "/github-release/Stellarium/stellarium",
      "status": "S1675509395X1675552595",
      "help": "",
      "upstream": "https://api.github.com/repos/"
    },
    {
      "cname": "termux",
      "desc": "运行在 Android 上的终端模拟器 Termux 的官方软件包仓库",
      "url": "/termux",
      "status": "S1675511230X1675518430",
      "help": "/help/termux/",
      "upstream": "rsync://mirrors.bfsu.edu.cn/termux/",
      "size": "18.16G"
    },
    {
      "cname": "texstudio",
      "desc": "使用 Qt 编写的自由的 LaTeX 套件",
      "url": "/github-release/texstudio-org/texstudio",
      "status": "S1675509395X1675552595",
      "help": "",
      "upstream": "https://api.github.com/repos/"
    },
    {
      "cname": "thuthesis",
      "desc": "清华大学学位论文 LaTeX 模板",
      "url": "/github-release/tuna/thuthesis",
      "status": "S1675509395X1675552595",
      "help": "",
      "upstream": "https://api.github.com/repos/"
    },
    {
      "cname": "tinycorelinux",
      "desc": "为嵌入式开发的微型 Linux 发行版",
      "url": "/tinycorelinux",
      "status": "S1675504431X1675518831",
      "help": "",
      "upstream": "rsync://www.tinycorelinux.net/tc/",
      "size": "287.34G"
    },
    {
      "cname": "trisquel",
      "desc": "",
      "url": "/trisquel",
      "status": "S1675504019X1675518419",
      "help": "",
      "upstream": "rsync://rsync.trisquel.info/trisquel.packages/",
      "size": "1.05T"
    },
    {
      "cname": "tuna",
      "desc": "TUNA 协会资料存档",
      "url": "/tuna",
      "status": "S",
      "help": "",
      "upstream": "cloud.tsinghua.edu.cn"
    },
    {
      "cname": "ubuntu",
      "desc": "流行的 Linux 发行版 Ubuntu 的安装镜像和官方软件包仓库",
      "url": "/ubuntu",
      "status": "S1675513747X1675528147",
      "help": "/help/ubuntu/",
      "upstream": "rsync://releases.ubuntu.com/ubuntu/",
      "size": "2.17T"
    },
    {
      "cname": "ubuntu-cdimage",
      "desc": "Ubuntu 及 Ubuntu 衍生版各版本安装镜像",
      "url": "/ubuntu-cdimage",
      "status": "Y1675509909O1675495507",
      "help": "",
      "upstream": "rsync://cdimage.ubuntu.com/cdimage/",
      "size": "1.26T"
    },
    {
      "cname": "ubuntu-cloud-images",
      "desc": "适用于公有云的 Ubuntu 安装镜像",
      "url": "/ubuntu-cloud-images",
      "status": "S1675510864X1675525264",
      "help": "/help/ubuntu-cloud-images/",
      "upstream": "rsync://cloud-images.ubuntu.com/cloud-images/",
      "size": "1.19T"
    },
    {
      "cname": "ubuntu-ports",
      "desc": "armhf, arm64 以及 powerpc 等平台的 Ubuntu 软件仓库",
      "url": "/ubuntu-ports",
      "status": "S1675512094X1675526494",
      "help": "/help/ubuntu-ports/",
      "upstream": "rsync://ports.ubuntu.com/ubuntu-ports/",
      "size": "2.59T"
    },
    {
      "cname": "ubuntu-releases",
      "desc": "包含近几年发行的 Ubuntu 的镜像",
      "url": "/ubuntu-releases",
      "status": "S1675512920X1675527320",
      "help": "",
      "upstream": "rsync://rsync.releases.ubuntu.com/releases/",
      "size": "29.00G"
    },
    {
      "cname": "ubuntukylin",
      "desc": "",
      "url": "/ubuntukylin",
      "status": "S1675512647X1675527047",
      "help": "",
      "upstream": "rsync://archive.ubuntukylin.com/ubuntukylin/",
      "size": "40.98G"
    },
    {
      "cname": "videolan-ftp",
      "desc": "简称VLC，是一款自由、开源的跨平台多媒体播放器及框架，可播放大多数多媒体文件",
      "url": "/videolan-ftp",
      "status": "S1675513176X1675527576",
      "help": "",
      "upstream": "rsync://rsync.videolan.org/videolan-ftp/",
      "size": "102.61G"
    },
    {
      "cname": "virtualbox",
      "desc": "Oracle 的开源的 x86 架构虚拟机",
      "url": "/virtualbox",
      "status": "S1675514444X1675521644",
      "help": "/help/virtualbox/",
      "upstream": "rsync://mirrors.bfsu.edu.cn/virtualbox/",
      "size": "169.62G"
    },
    {
      "cname": "voidlinux",
      "desc": "基于 xbps 包管理器的独立 Linux 发行版",
      "url": "/voidlinux",
      "status": "S1675516555X1675530955",
      "help": "/help/voidlinux/",
      "upstream": "rsync://mirror.clarkson.edu/voidlinux/",
      "size": "1.33T"
    },
    {
      "cname": "VSCodium",
      "desc": "VS Code 的社区编译版本",
      "url": "/github-release/VSCodium/vscodium",
      "status": "S1675509395X1675552595",
      "help": "",
      "upstream": "https://api.github.com/repos/"
    },
    {
      "cname": "winehq",
      "desc": "Wine （允许类 Unix 操作系统运行 Windows 程序）",
      "url": "/winehq",
      "status": "S1675515288X1675522488",
      "help": "",
      "upstream": "rsync://mirrors.bfsu.edu.cn/winehq/",
      "size": "44.46G"
    },
    {
      "cname": "xbot",
      "desc": "",
      "url": "/xbot",
      "status": "S1675513506X1675527906",
      "help": "",
      "upstream": "https://isrc.iscas.ac.cn/mirror/xbot/",
      "size": "53M"
    },
    {
      "cname": "zabbix",
      "desc": "著名的网络监视、管理系统",
      "url": "/zabbix",
      "status": "S1675507836X1675522236",
      "help": "",
      "upstream": "rsync://repo.zabbix.com/mirror/",
      "size": "146.32G"
    }
  ]
}