{
  "site": {
    "url": "https://mirrors.qlu.edu.cn",
    "logo": "https://mirrors.qlu.edu.cn/static/img/logo-small@4x.png",
    "abbr": "QLUT",
    "name": "齐鲁工业大学开源软件镜像站",
    "issue": "https://github.com/qlu-mirrors/issues",
    "request": "https://github.com/qlu-mirrors/issues",
    "big": "/speedtest/1000MB.bin",
    "disk": "429.66MiB/960.00MiB"
  },
  "info": [],
  "mirrors": [
    {
      "cname": "archlinux",
      "options_name": "archlinux",
      "url": "/archlinux",
      "status": "F1779108989O1779065786X1779152189",
      "upstream": "rsync://mirrors.tuna.tsinghua.edu.cn/archlinux/",
      "size": "129.64G",
      "desc": "Arch Linux 的安装镜像和官方软件包仓库",
      "help": "/help/archlinux/"
    },
    {
      "cname": "archlinuxarm",
      "options_name": "archlinuxarm",
      "url": "/archlinuxarm",
      "status": "F1779110884O1779067681X1779154084",
      "upstream": "rsync://ftp.halifax.rwth-aachen.de/archlinux-arm/",
      "size": "119.84G",
      "desc": "用于 ARM 平台的 Arch Linux 镜像和软件包仓库",
      "help": "/help/archlinuxarm/"
    },
    {
      "cname": "archlinuxcn",
      "options_name": "archlinuxcn",
      "url": "/archlinuxcn",
      "status": "S1779102517X1779145717",
      "upstream": "rsync://mirrors.tuna.tsinghua.edu.cn/archlinuxcn/",
      "size": "136.08G",
      "desc": "由 Arch Linux 中文社区驱动的非官方用户仓库，包含中文用户常用软件、工具、字体/美化包等",
      "help": "/help/archlinuxcn/"
    },
    {
      "cname": "armbian",
      "options_name": "armbian",
      "url": "/armbian",
      "status": "S1779091783X1779134983",
      "upstream": "rsync://rsync.armbian.com/apt/",
      "size": "82.30G",
      "desc": "Armbian（面向 ARM 单板机的发行版）的软件源",
      "help": "/help/armbian/"
    },
    {
      "cname": "bmclapi",
      "options_name": "bmclapi",
      "url": "/bmclapi",
      "status": "S1779095710X1779138910",
      "upstream": "rsync://s3p.933.moe/bmclapi/maven/",
      "size": "110.22G"
    },
    {
      "cname": "centos",
      "options_name": "centos",
      "url": "/centos",
      "status": "S1779094069X1779137269",
      "upstream": "rsync://mirrors.tuna.tsinghua.edu.cn/centos/",
      "size": "2.67M",
      "desc": "CentOS 的安装镜像和官方软件包仓库",
      "help": "/help/centos/"
    },
    {
      "cname": "centos-altarch",
      "options_name": "centos-altarch",
      "url": "/centos-altarch",
      "status": "S1779094089X1779137289",
      "upstream": "rsync://mirrors.tuna.tsinghua.edu.cn/centos-altarch/",
      "size": "4.06K",
      "desc": "CentOS 额外平台的安装镜像和官方软件包仓库",
      "help": "/help/centos-altarch/"
    },
    {
      "cname": "centos-stream",
      "options_name": "centos-stream",
      "url": "/centos-stream",
      "status": "F1779111432O1779044269X1779133032",
      "upstream": "rsync://rsync.stream.centos.org/CentOS-Stream-All/",
      "size": "3.00T",
      "help": "/help/centos-stream/"
    },
    {
      "cname": "ceph",
      "options_name": "ceph",
      "url": "/ceph",
      "status": "S1779094256X1779137456",
      "upstream": "rsync://mirrors.tuna.tsinghua.edu.cn/ceph/",
      "size": "296.66G",
      "desc": "高性能对象存储和文件系统",
      "help": "/help/ceph/"
    },
    {
      "cname": "CRAN",
      "options_name": "CRAN",
      "url": "/CRAN",
      "status": "S1779092473X1779135673",
      "upstream": "rsync://cran.r-project.org/CRAN/",
      "size": "681.43G",
      "desc": "R 语言的可执行文件、源代码和说明文件，也收录了各种用户撰写的软件包",
      "help": "/help/CRAN/"
    },
    {
      "cname": "CTAN",
      "options_name": "CTAN",
      "url": "/CTAN",
      "status": "S1779095568X1779138768",
      "upstream": "rsync://rsync.dante.ctan.org/CTAN/",
      "size": "68.15G",
      "desc": "TeX 的各种发行版、软件包和文档",
      "help": "/help/CTAN/"
    },
    {
      "cname": "debian",
      "options_name": "debian",
      "url": "/debian",
      "status": "S1779086917X1779130117",
      "upstream": "rsync://ftp.cn.debian.org/debian/",
      "size": "2.3T",
      "desc": "Debian Linux 的官方软件包仓库",
      "help": "/help/debian/"
    },
    {
      "cname": "debian-cd",
      "options_name": "debian-cd",
      "url": "/debian-cd",
      "status": "S1779098185X1779141385",
      "upstream": "rsync://mirrors.bfsu.edu.cn/debian-cd/",
      "size": "253.52G",
      "desc": "Debian Linux 的安装镜像"
    },
    {
      "cname": "deepin",
      "options_name": "deepin",
      "url": "/deepin",
      "status": "S1779102096X1779145296",
      "upstream": "rsync://mirrors.bfsu.edu.cn/deepin/",
      "size": "1.66T",
      "desc": "Deepin Linux 的官方软件包仓库"
    },
    {
      "cname": "deepin-cd",
      "options_name": "deepin-cd",
      "url": "/deepin-cd",
      "status": "S1779094067X1779137267",
      "upstream": "rsync://rsync.deepin.com/releases/",
      "size": "80.27G",
      "desc": "Deepin Linux 的安装镜像"
    },
    {
      "cname": "epel",
      "options_name": "epel",
      "url": "/epel",
      "status": "S1779102608X1779145808",
      "upstream": "rsync://mirrors.tuna.tsinghua.edu.cn/epel/",
      "size": "1.17T",
      "desc": "企业版 Linux 附加软件包",
      "help": "/help/epel/"
    },
    {
      "cname": "fedora",
      "options_name": "fedora",
      "url": "/fedora",
      "status": "S1779101342X1779122942",
      "upstream": "rsync://mirrors.tuna.tsinghua.edu.cn/fedora/",
      "size": "2.25T",
      "desc": "Fedora Linux 的安装镜像和官方软件包仓库",
      "help": "/help/fedora/"
    },
    {
      "cname": "fedora-altarch",
      "options_name": "fedora-altarch",
      "url": "/fedora-altarch",
      "status": "S1779094120X1779137320",
      "upstream": "rsync://mirrors.tuna.tsinghua.edu.cn/fedora-altarch/",
      "size": "15.77K",
      "desc": "Fedora Linux 额外平台的安装镜像和官方软件包仓库"
    },
    {
      "cname": "kali",
      "options_name": "kali",
      "url": "/kali",
      "status": "F1779117469O1779103068X1779131869",
      "upstream": "rsync://archive.kali.org/kali/",
      "size": "751G",
      "desc": "Kali Linux 的官方软件包仓库",
      "help": "/help/kali/"
    },
    {
      "cname": "kali-images",
      "options_name": "kali-images",
      "url": "/kali-images",
      "status": "F1779107989O1779064784X1779151189",
      "upstream": "rsync://archive.kali.org/kali-images/",
      "size": "114G",
      "desc": "Kali Linux 的安装镜像"
    },
    {
      "cname": "kernel",
      "options_name": "kernel",
      "url": "/kernel",
      "status": "S1779094924X1779138124",
      "upstream": "rsync://mirrors.tuna.tsinghua.edu.cn/kernel/",
      "size": "1.55T",
      "desc": "各个版本的 Linux 内核源代码压缩包和补丁"
    },
    {
      "cname": "loongson",
      "options_name": "loongson",
      "url": "/loongson",
      "status": "S1779094040X1779137240",
      "upstream": "rsync://mirrors.tuna.tsinghua.edu.cn/loongson/",
      "size": "24.00G",
      "desc": "用于龙芯电脑的软件包"
    },
    {
      "cname": "msys2",
      "options_name": "msys2",
      "url": "/msys2",
      "status": "F1779110084O1779066879X1779153284",
      "upstream": "rsync://mirrors.ustc.edu.cn/msys2/",
      "size": "1.51T",
      "desc": "用于编译原生 Windows 程序的类 Linux 开发环境",
      "help": "/help/msys2/"
    },
    {
      "cname": "rocky",
      "options_name": "rocky",
      "url": "/rocky",
      "status": "S1779090410X1779133610",
      "upstream": "rsync://msync.rockylinux.org/rocky/mirror/pub/rocky/",
      "size": "5.96T"
    },
    {
      "cname": "ros",
      "options_name": "ros",
      "url": "/ros",
      "status": "S1779094791X1779137991",
      "upstream": "rsync://mirrors.tuna.tsinghua.edu.cn/ros/",
      "size": "128.50G",
      "desc": "ROS 提供一系列程序库和工具以帮助软件开发者创建机器人应用软件",
      "help": "/help/ros/"
    },
    {
      "cname": "ros2",
      "options_name": "ros2",
      "url": "/ros2",
      "status": "S1779094724X1779137924",
      "upstream": "rsync://mirrors.tuna.tsinghua.edu.cn/ros2/",
      "size": "102.70G",
      "desc": "ROS (Robot Operating System) 2.0 版本",
      "help": "/help/ros2/"
    },
    {
      "cname": "termux",
      "options_name": "termux",
      "url": "/termux",
      "status": "S1779101152X1779144352",
      "upstream": "rsync://packages.termux.dev/termux/",
      "size": "42.34G",
      "desc": "运行在 Android 上的终端模拟器 Termux 的官方软件包仓库",
      "help": "/help/termux/"
    },
    {
      "cname": "tuna",
      "url": "/tuna",
      "status": "U",
      "upstream": "cloud.tsinghua.edu.cn"
    },
    {
      "cname": "ubuntu",
      "options_name": "ubuntu",
      "url": "/ubuntu",
      "status": "F1779114459O1779071257X1779157659",
      "upstream": "rsync://rsync.archive.ubuntu.com/ubuntu/",
      "size": "5.17T",
      "desc": "流行的 Linux 发行版 Ubuntu 的安装镜像和官方软件包仓库",
      "help": "/help/ubuntu/"
    },
    {
      "cname": "ubuntu-cdimage",
      "options_name": "ubuntu-cdimage",
      "url": "/ubuntu-cdimage",
      "status": "S1779103287X1779146487",
      "upstream": "rsync://mirrors.tuna.tsinghua.edu.cn/ubuntu-cdimage/",
      "size": "1.10T",
      "desc": "Ubuntu 及 Ubuntu 衍生版各版本安装镜像"
    },
    {
      "cname": "ubuntu-releases",
      "options_name": "ubuntu-releases",
      "url": "/ubuntu-releases",
      "status": "S1779100668X1779143868",
      "upstream": "rsync://rsync.releases.ubuntu.com/releases/",
      "size": "59.36G",
      "desc": "包含近几年发行的 Ubuntu 的镜像"
    },
    {
      "cname": "ubuntukylin",
      "options_name": "ubuntukylin",
      "url": "/ubuntukylin",
      "status": "S1779094079X1779137279",
      "upstream": "rsync://mirrors.tuna.tsinghua.edu.cn/ubuntukylin/",
      "size": "5.24G"
    },
    {
      "cname": "ubuntukylin-cdimage",
      "options_name": "ubuntukylin-cdimage",
      "url": "/ubuntukylin-cdimage",
      "status": "S1779094099X1779137299",
      "upstream": "rsync://mirrors.tuna.tsinghua.edu.cn/ubuntukylin-cdimage/",
      "size": "8.85G"
    }
  ],
  "endpoints": [
    {
      "label": "qlut",
      "public": true,
      "resolve": "mirrors.qlu.edu.cn",
      "filter": [
        "V4",
        "SSL",
        "NOSSL"
      ],
      "range": [
        "COUNTRY:CN",
        "REGION:SD",
        "ISP:CERNET"
      ]
    },
    {
      "label": "qlut6",
      "public": true,
      "resolve": "mirrors.qlu.edu.cn",
      "filter": [
        "V6",
        "NOSSL"
      ],
      "range": [
        "COUNTRY:CN",
        "REGION:SD",
        "ISP:CERNET"
      ]
    }
  ],
  "extension": "D"
}