{
  "application": "SCAU_OSSM_Mirrorz",
  "refresh": "2025-01-24 21:20:01",
  "author": "wangzt(interestingcn01@gmail.com)",
  "extension": "D",
  "endpoints": [
    {
      "label": "SCAU",
      "public": true,
      "resolve": "mirrors.scau.edu.cn",
      "filter": [
        "V4",
        "SSL"
      ],
      "range": [
        "COUNTRY:CN",
        "REGION:GD"
      ]
    }
  ],
  "site": {
    "url": "https://mirrors.scau.edu.cn",
    "logo": "https://mirrors.scau.edu.cn/static/img/scau_green_logo.png",
    "logo_darkmode": "https://mirrors.scau.edu.cn/static/img/scau_white_logo.png",
    "abbr": "SCAU",
    "name": "华南农业大学开源软件镜像站",
    "homepage": "https://mirrors.scau.edu.cn",
    "email": "mirrors@scau.edu.cn",
    "note": "欢迎访问华南农业大学开源软件镜像站",
    "disable": false
  },
  "info": [
    {
      "distro": "archlinux",
      "category": "os",
      "urls": [
        {
          "name": "2025.01.01 (x86_64, CLI-only)",
          "url": "/archlinux/iso/latest/archlinux-2025.01.01-x86_64.iso"
        }
      ]
    },
    {
      "distro": "debian",
      "category": "os",
      "urls": [
        {
          "name": "12.9.0 (amd64, Network installer)",
          "url": "/debian-cd/current/amd64/iso-cd/debian-12.9.0-amd64-netinst.iso"
        },
        {
          "name": "12.9.0 (amd64, Live CD with xfce)",
          "url": "/debian-cd/current-live/amd64/iso-hybrid/debian-live-12.9.0-amd64-xfce.iso"
        },
        {
          "name": "12.9.0 (amd64, Live CD with standard)",
          "url": "/debian-cd/current-live/amd64/iso-hybrid/debian-live-12.9.0-amd64-standard.iso"
        },
        {
          "name": "12.9.0 (amd64, Live CD with mate)",
          "url": "/debian-cd/current-live/amd64/iso-hybrid/debian-live-12.9.0-amd64-mate.iso"
        },
        {
          "name": "12.9.0 (amd64, Live CD with lxqt)",
          "url": "/debian-cd/current-live/amd64/iso-hybrid/debian-live-12.9.0-amd64-lxqt.iso"
        },
        {
          "name": "12.9.0 (amd64, Live CD with lxde)",
          "url": "/debian-cd/current-live/amd64/iso-hybrid/debian-live-12.9.0-amd64-lxde.iso"
        },
        {
          "name": "12.9.0 (amd64, Live CD with kde)",
          "url": "/debian-cd/current-live/amd64/iso-hybrid/debian-live-12.9.0-amd64-kde.iso"
        },
        {
          "name": "12.9.0 (amd64, Live CD with gnome)",
          "url": "/debian-cd/current-live/amd64/iso-hybrid/debian-live-12.9.0-amd64-gnome.iso"
        },
        {
          "name": "12.9.0 (amd64, Live CD with cinnamon)",
          "url": "/debian-cd/current-live/amd64/iso-hybrid/debian-live-12.9.0-amd64-cinnamon.iso"
        },
        {
          "name": "12.9.0 (amd64, DVD installer (Part 1))",
          "url": "/debian-cd/current/amd64/iso-dvd/debian-12.9.0-amd64-DVD-1.iso"
        },
        {
          "name": "12.9.0 (i386, Network installer)",
          "url": "/debian-cd/current/i386/iso-cd/debian-12.9.0-i386-netinst.iso"
        },
        {
          "name": "12.9.0 (i386, DVD installer (Part 1))",
          "url": "/debian-cd/current/i386/iso-dvd/debian-12.9.0-i386-DVD-1.iso"
        }
      ]
    },
    {
      "distro": "Docker",
      "category": "app",
      "urls": [
        {
          "name": "27.5.0 (Windows)",
          "url": "/docker-ce/win/static/stable/x86_64/docker-27.5.0.zip"
        },
        {
          "name": "27.5.0 (macOS)",
          "url": "/docker-ce/mac/static/stable/x86_64/docker-27.5.0.tgz"
        }
      ]
    },
    {
      "distro": "fedora",
      "category": "os",
      "urls": [
        {
          "name": "41 (x86_64, Silverblue ostree)",
          "url": "/fedora/releases/41/Silverblue/x86_64/iso/Fedora-Silverblue-ostree-x86_64-41-1.4.iso"
        },
        {
          "name": "41 (x86_64, Server netinst)",
          "url": "/fedora/releases/41/Server/x86_64/iso/Fedora-Server-netinst-x86_64-41-1.4.iso"
        },
        {
          "name": "41 (x86_64, Server dvd)",
          "url": "/fedora/releases/41/Server/x86_64/iso/Fedora-Server-dvd-x86_64-41-1.4.iso"
        },
        {
          "name": "41 (x86_64, Live CD with standard workstation desktop environment)",
          "url": "/fedora/releases/41/Workstation/x86_64/iso/Fedora-Workstation-Live-x86_64-41-1.4.iso"
        },
        {
          "name": "41 (x86_64, Live CD with i3)",
          "url": "/fedora/releases/41/Spins/x86_64/iso/Fedora-i3-Live-x86_64-41-1.4.iso"
        },
        {
          "name": "41 (x86_64, Live CD with Xfce)",
          "url": "/fedora/releases/41/Spins/x86_64/iso/Fedora-Xfce-Live-x86_64-41-1.4.iso"
        },
        {
          "name": "41 (x86_64, Live CD with Sway)",
          "url": "/fedora/releases/41/Spins/x86_64/iso/Fedora-Sway-Live-x86_64-41-1.4.iso"
        },
        {
          "name": "41 (x86_64, Live CD with SoaS)",
          "url": "/fedora/releases/41/Spins/x86_64/iso/Fedora-SoaS-Live-x86_64-41-1.4.iso"
        },
        {
          "name": "41 (x86_64, Live CD with MATE_Compiz)",
          "url": "/fedora/releases/41/Spins/x86_64/iso/Fedora-MATE_Compiz-Live-x86_64-41-1.4.iso"
        },
        {
          "name": "41 (x86_64, Live CD with LXQt)",
          "url": "/fedora/releases/41/Spins/x86_64/iso/Fedora-LXQt-Live-x86_64-41-1.4.iso"
        },
        {
          "name": "41 (x86_64, Live CD with LXDE)",
          "url": "/fedora/releases/41/Spins/x86_64/iso/Fedora-LXDE-Live-x86_64-41-1.4.iso"
        },
        {
          "name": "41 (x86_64, Live CD with KDE)",
          "url": "/fedora/releases/41/Spins/x86_64/iso/Fedora-KDE-Live-x86_64-41-1.4.iso"
        },
        {
          "name": "41 (x86_64, Live CD with Cinnamon)",
          "url": "/fedora/releases/41/Spins/x86_64/iso/Fedora-Cinnamon-Live-x86_64-41-1.4.iso"
        },
        {
          "name": "41 (x86_64, Live CD with Budgie)",
          "url": "/fedora/releases/41/Spins/x86_64/iso/Fedora-Budgie-Live-x86_64-41-1.4.iso"
        },
        {
          "name": "41 (x86_64, Everything netinst)",
          "url": "/fedora/releases/41/Everything/x86_64/iso/Fedora-Everything-netinst-x86_64-41-1.4.iso"
        },
        {
          "name": "41 (aarch64, Silverblue ostree)",
          "url": "/fedora/releases/41/Silverblue/aarch64/iso/Fedora-Silverblue-ostree-aarch64-41-1.4.iso"
        },
        {
          "name": "41 (aarch64, Server netinst)",
          "url": "/fedora/releases/41/Server/aarch64/iso/Fedora-Server-netinst-aarch64-41-1.4.iso"
        },
        {
          "name": "41 (aarch64, Server dvd)",
          "url": "/fedora/releases/41/Server/aarch64/iso/Fedora-Server-dvd-aarch64-41-1.4.iso"
        },
        {
          "name": "41 (aarch64, Live CD with LXQt)",
          "url": "/fedora/releases/41/Spins/aarch64/iso/Fedora-LXQt-Live-aarch64-41-1.4.iso"
        },
        {
          "name": "41 (aarch64, Live CD with KDE)",
          "url": "/fedora/releases/41/Spins/aarch64/iso/Fedora-KDE-Live-aarch64-41-1.4.iso"
        },
        {
          "name": "41 (aarch64, Everything netinst)",
          "url": "/fedora/releases/41/Everything/aarch64/iso/Fedora-Everything-netinst-aarch64-41-1.4.iso"
        },
        {
          "name": "40 (x86_64, Silverblue ostree)",
          "url": "/fedora/releases/40/Silverblue/x86_64/iso/Fedora-Silverblue-ostree-x86_64-40-1.14.iso"
        },
        {
          "name": "40 (x86_64, Server netinst)",
          "url": "/fedora/releases/40/Server/x86_64/iso/Fedora-Server-netinst-x86_64-40-1.14.iso"
        },
        {
          "name": "40 (x86_64, Server dvd)",
          "url": "/fedora/releases/40/Server/x86_64/iso/Fedora-Server-dvd-x86_64-40-1.14.iso"
        },
        {
          "name": "40 (x86_64, Live CD with standard workstation desktop environment)",
          "url": "/fedora/releases/40/Workstation/x86_64/iso/Fedora-Workstation-Live-x86_64-40-1.14.iso"
        },
        {
          "name": "40 (x86_64, Live CD with i3)",
          "url": "/fedora/releases/40/Spins/x86_64/iso/Fedora-i3-Live-x86_64-40-1.14.iso"
        },
        {
          "name": "40 (x86_64, Live CD with Xfce)",
          "url": "/fedora/releases/40/Spins/x86_64/iso/Fedora-Xfce-Live-x86_64-40-1.14.iso"
        },
        {
          "name": "40 (x86_64, Live CD with Sway)",
          "url": "/fedora/releases/40/Spins/x86_64/iso/Fedora-Sway-Live-x86_64-40-1.14.iso"
        },
        {
          "name": "40 (x86_64, Live CD with SoaS)",
          "url": "/fedora/releases/40/Spins/x86_64/iso/Fedora-SoaS-Live-x86_64-40-1.14.iso"
        },
        {
          "name": "40 (x86_64, Live CD with MATE_Compiz)",
          "url": "/fedora/releases/40/Spins/x86_64/iso/Fedora-MATE_Compiz-Live-x86_64-40-1.14.iso"
        },
        {
          "name": "40 (x86_64, Live CD with LXQt)",
          "url": "/fedora/releases/40/Spins/x86_64/iso/Fedora-LXQt-Live-x86_64-40-1.14.iso"
        },
        {
          "name": "40 (x86_64, Live CD with LXDE)",
          "url": "/fedora/releases/40/Spins/x86_64/iso/Fedora-LXDE-Live-x86_64-40-1.14.iso"
        },
        {
          "name": "40 (x86_64, Live CD with KDE)",
          "url": "/fedora/releases/40/Spins/x86_64/iso/Fedora-KDE-Live-x86_64-40-1.14.iso"
        },
        {
          "name": "40 (x86_64, Live CD with Cinnamon)",
          "url": "/fedora/releases/40/Spins/x86_64/iso/Fedora-Cinnamon-Live-x86_64-40-1.14.iso"
        },
        {
          "name": "40 (x86_64, Live CD with Budgie)",
          "url": "/fedora/releases/40/Spins/x86_64/iso/Fedora-Budgie-Live-x86_64-40-1.14.iso"
        },
        {
          "name": "40 (x86_64, Everything netinst)",
          "url": "/fedora/releases/40/Everything/x86_64/iso/Fedora-Everything-netinst-x86_64-40-1.14.iso"
        },
        {
          "name": "40 (aarch64, Silverblue ostree)",
          "url": "/fedora/releases/40/Silverblue/aarch64/iso/Fedora-Silverblue-ostree-aarch64-40-1.14.iso"
        },
        {
          "name": "40 (aarch64, Server netinst)",
          "url": "/fedora/releases/40/Server/aarch64/iso/Fedora-Server-netinst-aarch64-40-1.14.iso"
        },
        {
          "name": "40 (aarch64, Server dvd)",
          "url": "/fedora/releases/40/Server/aarch64/iso/Fedora-Server-dvd-aarch64-40-1.14.iso"
        },
        {
          "name": "40 (osb, Live CD with standard workstation desktop environment)",
          "url": "/fedora/releases/40/Workstation/x86_64/iso/Fedora-Workstation-Live-osb-40-1.14.x86_64.iso"
        },
        {
          "name": "40 (osb, Live CD with standard workstation desktop environment)",
          "url": "/fedora/releases/40/Workstation/aarch64/iso/Fedora-Workstation-Live-osb-40-1.14.aarch64.iso"
        },
        {
          "name": "40 (aarch64, Everything netinst)",
          "url": "/fedora/releases/40/Everything/aarch64/iso/Fedora-Everything-netinst-aarch64-40-1.14.iso"
        }
      ]
    },
    {
      "distro": "kali",
      "category": "os",
      "urls": [
        {
          "name": "2024.4 (amd64, live)",
          "url": "/kali-images/current/kali-linux-2024.4-live-amd64.iso"
        },
        {
          "name": "2024.4 (amd64, installer-purple)",
          "url": "/kali-images/current/kali-linux-2024.4-installer-purple-amd64.iso"
        },
        {
          "name": "2024.4 (amd64, installer-netinst)",
          "url": "/kali-images/current/kali-linux-2024.4-installer-netinst-amd64.iso"
        },
        {
          "name": "2024.4 (amd64, installer)",
          "url": "/kali-images/current/kali-linux-2024.4-installer-amd64.iso"
        },
        {
          "name": "2024.4 (arm64, live)",
          "url": "/kali-images/current/kali-linux-2024.4-live-arm64.iso"
        },
        {
          "name": "2024.4 (arm64, installer-netinst)",
          "url": "/kali-images/current/kali-linux-2024.4-installer-netinst-arm64.iso"
        },
        {
          "name": "2024.4 (arm64, installer)",
          "url": "/kali-images/current/kali-linux-2024.4-installer-arm64.iso"
        }
      ]
    },
    {
      "distro": "linuxmint",
      "category": "os",
      "urls": [
        {
          "name": "LMDE 6 (64bit, cinnamon)",
          "url": "/linuxmint-cd/debian/lmde-6-cinnamon-64bit.iso"
        },
        {
          "name": "LMDE 6 (32bit, cinnamon)",
          "url": "/linuxmint-cd/debian/lmde-6-cinnamon-32bit.iso"
        },
        {
          "name": "22.1 (64bit, xfce)",
          "url": "/linuxmint-cd/stable/22.1/linuxmint-22.1-xfce-64bit.iso"
        },
        {
          "name": "22.1 (64bit, mate)",
          "url": "/linuxmint-cd/stable/22.1/linuxmint-22.1-mate-64bit.iso"
        },
        {
          "name": "22.1 (64bit, cinnamon)",
          "url": "/linuxmint-cd/stable/22.1/linuxmint-22.1-cinnamon-64bit.iso"
        }
      ]
    },
    {
      "distro": "putty",
      "category": "app",
      "urls": [
        {
          "name": "0.82 (Windows, 32-bit x86, puttygen.exe)",
          "url": "/putty/0.82/w32/puttygen.exe"
        },
        {
          "name": "0.82 (Windows, 64-bit x86, puttygen.exe)",
          "url": "/putty/0.82/w64/puttygen.exe"
        },
        {
          "name": "0.82 (Windows, 32-bit Arm, puttygen.exe)",
          "url": "/putty/0.82/wa32/puttygen.exe"
        },
        {
          "name": "0.82 (Windows, 64-bit Arm, puttygen.exe)",
          "url": "/putty/0.82/wa64/puttygen.exe"
        },
        {
          "name": "0.82 (Windows, 32-bit x86, putty.zip)",
          "url": "/putty/0.82/w32/putty.zip"
        },
        {
          "name": "0.82 (Windows, 64-bit x86, putty.zip)",
          "url": "/putty/0.82/w64/putty.zip"
        },
        {
          "name": "0.82 (Windows, 32-bit Arm, putty.zip)",
          "url": "/putty/0.82/wa32/putty.zip"
        },
        {
          "name": "0.82 (Windows, 64-bit Arm, putty.zip)",
          "url": "/putty/0.82/wa64/putty.zip"
        },
        {
          "name": "0.82 (Windows, 32-bit x86, putty.exe)",
          "url": "/putty/0.82/w32/putty.exe"
        },
        {
          "name": "0.82 (Windows, 64-bit x86, putty.exe)",
          "url": "/putty/0.82/w64/putty.exe"
        },
        {
          "name": "0.82 (Windows, 32-bit Arm, putty.exe)",
          "url": "/putty/0.82/wa32/putty.exe"
        },
        {
          "name": "0.82 (Windows, 64-bit Arm, putty.exe)",
          "url": "/putty/0.82/wa64/putty.exe"
        },
        {
          "name": "0.82 (Windows, 64-bit Arm, putty-arm64-0.82-installer.msi)",
          "url": "/putty/0.82/wa64/putty-arm64-0.82-installer.msi"
        },
        {
          "name": "0.82 (Windows, 32-bit Arm, putty-arm32-0.82-installer.msi)",
          "url": "/putty/0.82/wa32/putty-arm32-0.82-installer.msi"
        },
        {
          "name": "0.82 (Windows, 64-bit x86, putty-64bit-0.82-installer.msi)",
          "url": "/putty/0.82/w64/putty-64bit-0.82-installer.msi"
        },
        {
          "name": "0.82 (Windows, 32-bit x86, putty-0.82-installer.msi)",
          "url": "/putty/0.82/w32/putty-0.82-installer.msi"
        }
      ]
    },
    {
      "distro": "R",
      "category": "app",
      "urls": [
        {
          "name": "devel (Windows, unstable)",
          "url": "/CRAN/bin/windows/base/R-devel-win.exe"
        },
        {
          "name": "4.4.2patched (Windows, unstable)",
          "url": "/CRAN/bin/windows/base/R-4.4.2patched-win.exe"
        },
        {
          "name": "4.4.2 (Windows)",
          "url": "/CRAN/bin/windows/base/R-4.4.2-win.exe"
        },
        {
          "name": "4.4.2 (macOS >= 11, x86_64)",
          "url": "/CRAN/bin/macosx/big-sur-x86_64/base/R-4.4.2-x86_64.pkg"
        },
        {
          "name": "4.4.2 (macOS >= 11, arm64)",
          "url": "/CRAN/bin/macosx/big-sur-arm64/base/R-4.4.2-arm64.pkg"
        },
        {
          "name": "4.2.3 (macOS >= 10.13)",
          "url": "/CRAN/bin/macosx/base/R-4.2.3.pkg"
        }
      ]
    },
    {
      "distro": "TeX 排版系统",
      "category": "app",
      "urls": [
        {
          "name": "TeX Live 2024 (Windows & Linux)",
          "url": "/CTAN/systems/texlive/Images/texlive2024-20240312.iso"
        },
        {
          "name": "MikTeX 24.1 (Windows, x64)",
          "url": "/CTAN/systems/win32/miktex/setup/windows-x64/basic-miktex-24.1-x64.exe"
        },
        {
          "name": "MikTeX 22.1 (macOS, x86_64)",
          "url": "/CTAN/systems/win32/miktex/setup/darwin-x86_64/miktex-22.1-darwin-x86_64.dmg"
        },
        {
          "name": "MacTeX 20240312 (macOS)",
          "url": "/CTAN/systems/mac/mactex/mactex-20240312.pkg"
        }
      ]
    },
    {
      "distro": "ubuntu",
      "category": "os",
      "urls": [
        {
          "name": "24.10 (amd64, Server)",
          "url": "/ubuntu-releases/oracular/ubuntu-24.10-live-server-amd64.iso"
        },
        {
          "name": "24.10 (amd64, Desktop LiveDVD)",
          "url": "/ubuntu-releases/oracular/ubuntu-24.10-desktop-amd64.iso"
        },
        {
          "name": "24.10 (arm64, Server)",
          "url": "/ubuntu-cdimage/releases/oracular/release/ubuntu-24.10-live-server-arm64.iso"
        },
        {
          "name": "24.10 (ppc64el, Server)",
          "url": "/ubuntu-cdimage/releases/oracular/release/ubuntu-24.10-live-server-ppc64el.iso"
        },
        {
          "name": "24.10 (s390x, Server)",
          "url": "/ubuntu-cdimage/releases/oracular/release/ubuntu-24.10-live-server-s390x.iso"
        },
        {
          "name": "24.10 (arm64+largemem, Server)",
          "url": "/ubuntu-cdimage/releases/oracular/release/ubuntu-24.10-live-server-arm64+largemem.iso"
        },
        {
          "name": "24.10 (riscv64+icicle, Preinstalled Server)",
          "url": "/ubuntu-cdimage/releases/oracular/release/ubuntu-24.10-preinstalled-server-riscv64+icicle.img.xz"
        },
        {
          "name": "24.10 (riscv64+milkvmars, Preinstalled Server)",
          "url": "/ubuntu-cdimage/releases/oracular/release/ubuntu-24.10-preinstalled-server-riscv64+milkvmars.img.xz"
        },
        {
          "name": "24.10 (riscv64+nezha, Preinstalled Server)",
          "url": "/ubuntu-cdimage/releases/oracular/release/ubuntu-24.10-preinstalled-server-riscv64+nezha.img.xz"
        },
        {
          "name": "24.10 (riscv64+licheerv, Preinstalled Server)",
          "url": "/ubuntu-cdimage/releases/oracular/release/ubuntu-24.10-preinstalled-server-riscv64+licheerv.img.xz"
        },
        {
          "name": "24.10 (riscv64+pic64gx, Preinstalled Server)",
          "url": "/ubuntu-cdimage/releases/oracular/release/ubuntu-24.10-preinstalled-server-riscv64+pic64gx.img.xz"
        },
        {
          "name": "24.10 (riscv64+visionfive2, Preinstalled Server)",
          "url": "/ubuntu-cdimage/releases/oracular/release/ubuntu-24.10-preinstalled-server-riscv64+visionfive2.img.xz"
        },
        {
          "name": "24.10 (riscv64, Preinstalled Server)",
          "url": "/ubuntu-cdimage/releases/oracular/release/ubuntu-24.10-preinstalled-server-riscv64.img.xz"
        },
        {
          "name": "24.10 (arm64+raspi, Preinstalled Server)",
          "url": "/ubuntu-cdimage/releases/oracular/release/ubuntu-24.10-preinstalled-server-arm64+raspi.img.xz"
        },
        {
          "name": "24.10 (riscv64+unmatched, Preinstalled Server)",
          "url": "/ubuntu-cdimage/releases/oracular/release/ubuntu-24.10-preinstalled-server-riscv64+unmatched.img.xz"
        },
        {
          "name": "24.10 (arm64+raspi, Preinstalled Desktop)",
          "url": "/ubuntu-cdimage/releases/oracular/release/ubuntu-24.10-preinstalled-desktop-arm64+raspi.img.xz"
        },
        {
          "name": "24.04.1 (amd64, Server)",
          "url": "/ubuntu-releases/noble/ubuntu-24.04.1-live-server-amd64.iso"
        },
        {
          "name": "24.04.1 (amd64, Desktop LiveDVD)",
          "url": "/ubuntu-releases/noble/ubuntu-24.04.1-desktop-amd64.iso"
        },
        {
          "name": "24.04.1 (arm64+largemem, Server)",
          "url": "/ubuntu-cdimage/releases/noble/release/ubuntu-24.04.1-live-server-arm64+largemem.iso"
        },
        {
          "name": "24.04.1 (arm64, Server)",
          "url": "/ubuntu-cdimage/releases/noble/release/ubuntu-24.04.1-live-server-arm64.iso"
        },
        {
          "name": "24.04.1 (s390x, Server)",
          "url": "/ubuntu-cdimage/releases/noble/release/ubuntu-24.04.1-live-server-s390x.iso"
        },
        {
          "name": "24.04.1 (ppc64el, Server)",
          "url": "/ubuntu-cdimage/releases/noble/release/ubuntu-24.04.1-live-server-ppc64el.iso"
        },
        {
          "name": "24.04.1 (riscv64+milkvmars, Preinstalled Server)",
          "url": "/ubuntu-cdimage/releases/noble/release/ubuntu-24.04.1-preinstalled-server-riscv64+milkvmars.img.xz"
        },
        {
          "name": "24.04.1 (riscv64+pic64gx, Preinstalled Server)",
          "url": "/ubuntu-cdimage/releases/noble/release/ubuntu-24.04.1-preinstalled-server-riscv64+pic64gx.img.xz"
        },
        {
          "name": "24.04.1 (riscv64, Preinstalled Server)",
          "url": "/ubuntu-cdimage/releases/noble/release/ubuntu-24.04.1-preinstalled-server-riscv64.img.xz"
        },
        {
          "name": "24.04.1 (riscv64+nezha, Preinstalled Server)",
          "url": "/ubuntu-cdimage/releases/noble/release/ubuntu-24.04.1-preinstalled-server-riscv64+nezha.img.xz"
        },
        {
          "name": "24.04.1 (riscv64+icicle, Preinstalled Server)",
          "url": "/ubuntu-cdimage/releases/noble/release/ubuntu-24.04.1-preinstalled-server-riscv64+icicle.img.xz"
        },
        {
          "name": "24.04.1 (arm64+raspi, Preinstalled Server)",
          "url": "/ubuntu-cdimage/releases/noble/release/ubuntu-24.04.1-preinstalled-server-arm64+raspi.img.xz"
        },
        {
          "name": "24.04.1 (riscv64+visionfive2, Preinstalled Server)",
          "url": "/ubuntu-cdimage/releases/noble/release/ubuntu-24.04.1-preinstalled-server-riscv64+visionfive2.img.xz"
        },
        {
          "name": "24.04.1 (riscv64+licheerv, Preinstalled Server)",
          "url": "/ubuntu-cdimage/releases/noble/release/ubuntu-24.04.1-preinstalled-server-riscv64+licheerv.img.xz"
        },
        {
          "name": "24.04.1 (riscv64+unmatched, Preinstalled Server)",
          "url": "/ubuntu-cdimage/releases/noble/release/ubuntu-24.04.1-preinstalled-server-riscv64+unmatched.img.xz"
        },
        {
          "name": "24.04.1 (arm64+raspi, Preinstalled Desktop)",
          "url": "/ubuntu-cdimage/releases/noble/release/ubuntu-24.04.1-preinstalled-desktop-arm64+raspi.img.xz"
        },
        {
          "name": "22.04.5 (amd64, Server)",
          "url": "/ubuntu-releases/jammy/ubuntu-22.04.5-live-server-amd64.iso"
        },
        {
          "name": "22.04.5 (amd64, Desktop LiveDVD)",
          "url": "/ubuntu-releases/jammy/ubuntu-22.04.5-desktop-amd64.iso"
        },
        {
          "name": "22.04.5 (s390x, Server)",
          "url": "/ubuntu-cdimage/releases/jammy/release/ubuntu-22.04.5-live-server-s390x.iso"
        },
        {
          "name": "22.04.5 (arm64+largemem, Server)",
          "url": "/ubuntu-cdimage/releases/jammy/release/ubuntu-22.04.5-live-server-arm64+largemem.iso"
        },
        {
          "name": "22.04.5 (ppc64el, Server)",
          "url": "/ubuntu-cdimage/releases/jammy/release/ubuntu-22.04.5-live-server-ppc64el.iso"
        },
        {
          "name": "22.04.5 (arm64, Server)",
          "url": "/ubuntu-cdimage/releases/jammy/release/ubuntu-22.04.5-live-server-arm64.iso"
        },
        {
          "name": "22.04.5 (riscv64+unmatched, Preinstalled Server)",
          "url": "/ubuntu-cdimage/releases/jammy/release/ubuntu-22.04.5-preinstalled-server-riscv64+unmatched.img.xz"
        },
        {
          "name": "22.04.5 (riscv64+nezha, Preinstalled Server)",
          "url": "/ubuntu-cdimage/releases/jammy/release/ubuntu-22.04.5-preinstalled-server-riscv64+nezha.img.xz"
        },
        {
          "name": "22.04.5 (riscv64+licheerv, Preinstalled Server)",
          "url": "/ubuntu-cdimage/releases/jammy/release/ubuntu-22.04.5-preinstalled-server-riscv64+licheerv.img.xz"
        },
        {
          "name": "22.04.5 (riscv64+icicle, Preinstalled Server)",
          "url": "/ubuntu-cdimage/releases/jammy/release/ubuntu-22.04.5-preinstalled-server-riscv64+icicle.img.xz"
        },
        {
          "name": "22.04.5 (riscv64+visionfive, Preinstalled Server)",
          "url": "/ubuntu-cdimage/releases/jammy/release/ubuntu-22.04.5-preinstalled-server-riscv64+visionfive.img.xz"
        },
        {
          "name": "22.04.5 (arm64+raspi, Preinstalled Server)",
          "url": "/ubuntu-cdimage/releases/jammy/release/ubuntu-22.04.5-preinstalled-server-arm64+raspi.img.xz"
        },
        {
          "name": "22.04.5 (armhf+raspi, Preinstalled Server)",
          "url": "/ubuntu-cdimage/releases/jammy/release/ubuntu-22.04.5-preinstalled-server-armhf+raspi.img.xz"
        },
        {
          "name": "22.04.5 (arm64+raspi, Preinstalled Desktop)",
          "url": "/ubuntu-cdimage/releases/jammy/release/ubuntu-22.04.5-preinstalled-desktop-arm64+raspi.img.xz"
        },
        {
          "name": "20.04.6 (amd64, Server)",
          "url": "/ubuntu-releases/focal/ubuntu-20.04.6-live-server-amd64.iso"
        },
        {
          "name": "20.04.6 (amd64, Desktop LiveDVD)",
          "url": "/ubuntu-releases/focal/ubuntu-20.04.6-desktop-amd64.iso"
        },
        {
          "name": "20.04.5 (arm64+raspi, Preinstalled Server)",
          "url": "/ubuntu-cdimage/releases/focal/release/ubuntu-20.04.5-preinstalled-server-arm64+raspi.img.xz"
        },
        {
          "name": "20.04.5 (riscv64+unmatched, Preinstalled Server)",
          "url": "/ubuntu-cdimage/releases/focal/release/ubuntu-20.04.5-preinstalled-server-riscv64+unmatched.img.xz"
        },
        {
          "name": "20.04.5 (armhf+raspi, Preinstalled Server)",
          "url": "/ubuntu-cdimage/releases/focal/release/ubuntu-20.04.5-preinstalled-server-armhf+raspi.img.xz"
        },
        {
          "name": "18.04.6 (amd64, Server)",
          "url": "/ubuntu-cdimage/releases/bionic/release/ubuntu-18.04.6-server-amd64.iso"
        },
        {
          "name": "18.04.6 (arm64, Server)",
          "url": "/ubuntu-cdimage/releases/bionic/release/ubuntu-18.04.6-server-arm64.iso"
        },
        {
          "name": "18.04.5 (ppc64el, Server)",
          "url": "/ubuntu-cdimage/releases/bionic/release/ubuntu-18.04.5-server-ppc64el.iso"
        },
        {
          "name": "18.04.5 (s390x, Server)",
          "url": "/ubuntu-cdimage/releases/bionic/release/ubuntu-18.04.5-server-s390x.iso"
        },
        {
          "name": "16.04.7 (amd64, Server)",
          "url": "/ubuntu-releases/xenial/ubuntu-16.04.7-server-amd64.iso"
        },
        {
          "name": "16.04.7 (arm64, Server)",
          "url": "/ubuntu-cdimage/releases/xenial/release/ubuntu-16.04.7-server-arm64.iso"
        },
        {
          "name": "16.04.6 (i386, Server)",
          "url": "/ubuntu-releases/xenial/ubuntu-16.04.6-server-i386.iso"
        },
        {
          "name": "16.04.6 (ppc64el, Server)",
          "url": "/ubuntu-cdimage/releases/xenial/release/ubuntu-16.04.6-server-ppc64el.iso"
        },
        {
          "name": "16.04.6 (s390x, Server)",
          "url": "/ubuntu-cdimage/releases/xenial/release/ubuntu-16.04.6-server-s390x.iso"
        },
        {
          "name": "16.04.6 (powerpc, Server)",
          "url": "/ubuntu-cdimage/releases/xenial/release/ubuntu-16.04.6-server-powerpc.iso"
        },
        {
          "name": "16.04.6 (arm64, Server)",
          "url": "/ubuntu-cdimage/releases/xenial/release/ubuntu-16.04.6-server-arm64.iso"
        }
      ]
    },
    {
      "distro": "Ubuntu Core",
      "category": "os",
      "urls": [
        {
          "name": "24 (amd64, .img.xz)",
          "url": "/ubuntu-cdimage/ubuntu-core/24/stable/current/ubuntu-core-24-amd64.img.xz"
        },
        {
          "name": "24 (arm64+raspi, .img.xz)",
          "url": "/ubuntu-cdimage/ubuntu-core/24/stable/current/ubuntu-core-24-arm64+raspi.img.xz"
        },
        {
          "name": "24 (arm64, .img.xz)",
          "url": "/ubuntu-cdimage/ubuntu-core/24/stable/current/ubuntu-core-24-arm64.img.xz"
        },
        {
          "name": "22 (amd64, .img.xz)",
          "url": "/ubuntu-cdimage/ubuntu-core/22/stable/current/ubuntu-core-22-amd64.img.xz"
        },
        {
          "name": "22 (amd64+intel-iot, .img.xz)",
          "url": "/ubuntu-cdimage/ubuntu-core/22/stable/current/ubuntu-core-22-amd64+intel-iot.img.xz"
        },
        {
          "name": "22 (arm64+raspi, .img.xz)",
          "url": "/ubuntu-cdimage/ubuntu-core/22/stable/current/ubuntu-core-22-arm64+raspi.img.xz"
        },
        {
          "name": "22 (arm64, .img.xz)",
          "url": "/ubuntu-cdimage/ubuntu-core/22/stable/current/ubuntu-core-22-arm64.img.xz"
        },
        {
          "name": "22 (armhf+raspi, .img.xz)",
          "url": "/ubuntu-cdimage/ubuntu-core/22/stable/current/ubuntu-core-22-armhf+raspi.img.xz"
        },
        {
          "name": "20 (amd64, .img.xz)",
          "url": "/ubuntu-cdimage/ubuntu-core/20/stable/current/ubuntu-core-20-amd64.img.xz"
        },
        {
          "name": "20 (amd64+intel-iot, .img.xz)",
          "url": "/ubuntu-cdimage/ubuntu-core/20/stable/current/ubuntu-core-20-amd64+intel-iot.img.xz"
        },
        {
          "name": "20 (arm64+raspi, .img.xz)",
          "url": "/ubuntu-cdimage/ubuntu-core/20/stable/current/ubuntu-core-20-arm64+raspi.img.xz"
        },
        {
          "name": "20 (armhf+raspi, .img.xz)",
          "url": "/ubuntu-cdimage/ubuntu-core/20/stable/current/ubuntu-core-20-armhf+raspi.img.xz"
        }
      ]
    },
    {
      "distro": "Ubuntu 衍生版",
      "category": "os",
      "urls": [
        {
          "name": "Xubuntu 24.10 (amd64)",
          "url": "/ubuntu-cdimage/xubuntu/releases/oracular/release/xubuntu-24.10-desktop-amd64.iso"
        },
        {
          "name": "Ubuntu Mate 24.10 (amd64)",
          "url": "/ubuntu-cdimage/ubuntu-mate/releases/oracular/release/ubuntu-mate-24.10-desktop-amd64.iso"
        },
        {
          "name": "Ubuntu Kylin 24.10 (amd64)",
          "url": "/ubuntu-cdimage/ubuntukylin/releases/oracular/release/ubuntukylin-24.10-desktop-amd64.iso"
        },
        {
          "name": "Ubuntu Gnome 16.04.5 (amd64)",
          "url": "/ubuntu-cdimage/ubuntu-gnome/releases/xenial/release/ubuntu-gnome-16.04.5-desktop-amd64.iso"
        },
        {
          "name": "Ubuntu Gnome 16.04.5 (i386)",
          "url": "/ubuntu-cdimage/ubuntu-gnome/releases/xenial/release/ubuntu-gnome-16.04.5-desktop-i386.iso"
        },
        {
          "name": "Lubuntu 24.10 (amd64)",
          "url": "/ubuntu-cdimage/lubuntu/releases/oracular/release/lubuntu-24.10-desktop-amd64.iso"
        },
        {
          "name": "Kubuntu 24.10 (amd64)",
          "url": "/ubuntu-cdimage/kubuntu/releases/oracular/release/kubuntu-24.10-desktop-amd64.iso"
        }
      ]
    }
  ],
  "mirrors": [
    {
      "cname": "archlinux",
      "desc": "",
      "url": "/archlinux",
      "status": "S1737722292X1737743892",
      "upstream": "rsync://mirrors.tuna.tsinghua.edu.cn/archlinux/",
      "help": "",
      "size": "114.13G"
    },
    {
      "cname": "armbian",
      "desc": "",
      "url": "/armbian",
      "status": "S1737724232X1737767432",
      "upstream": "rsync://mirrors.tuna.tsinghua.edu.cn/armbian/",
      "help": "",
      "size": "203.99G"
    },
    {
      "cname": "bioconductor",
      "desc": "",
      "url": "/bioconductor",
      "status": "S1737701334X1737744534",
      "upstream": "rsync://mirrors.tuna.tsinghua.edu.cn/bioconductor/",
      "help": "",
      "size": "724.16G"
    },
    {
      "cname": "centos-stream",
      "desc": "",
      "url": "/centos-stream",
      "status": "S1737682855X1737726055",
      "upstream": "rsync://mirrors.bfsu.edu.cn/centos-stream/",
      "help": "",
      "size": "3.54T"
    },
    {
      "cname": "ceph",
      "desc": "",
      "url": "/ceph",
      "status": "S1737724628X1737767828",
      "upstream": "rsync://mirrors.tuna.tsinghua.edu.cn/ceph/",
      "help": "",
      "size": "304.89G"
    },
    {
      "cname": "CPAN",
      "desc": "",
      "url": "/CPAN",
      "status": "S1737683346X1737726546",
      "upstream": "rsync://mirrors.tuna.tsinghua.edu.cn/CPAN/",
      "help": "",
      "size": "37.98G"
    },
    {
      "cname": "CRAN",
      "desc": "",
      "url": "/CRAN",
      "status": "S1737710046X1737753246",
      "upstream": "rsync://mirrors.tuna.tsinghua.edu.cn/CRAN/",
      "help": "",
      "size": "525.27G"
    },
    {
      "cname": "CTAN",
      "desc": "",
      "url": "/CTAN",
      "status": "S1737682283X1737725483",
      "upstream": "rsync://mirrors.tuna.tsinghua.edu.cn/CTAN/",
      "help": "",
      "size": "61.17G"
    },
    {
      "cname": "ctex",
      "desc": "",
      "url": "/ctex",
      "status": "S1737720142X1737763342",
      "upstream": "rsync://mirrors.bfsu.edu.cn/ctex/",
      "help": "",
      "size": "16.60G"
    },
    {
      "cname": "debian",
      "desc": "",
      "url": "/debian",
      "status": "S1737710349X1737753549",
      "upstream": "rsync://mirrors.tuna.tsinghua.edu.cn/debian/",
      "help": "",
      "size": "2.10T"
    },
    {
      "cname": "debian-cd",
      "desc": "",
      "url": "/debian-cd",
      "status": "S1737720099X1737763299",
      "upstream": "rsync://mirrors.tuna.tsinghua.edu.cn/debian-cd/",
      "help": "",
      "size": "235.49G"
    },
    {
      "cname": "debian-nonfree",
      "desc": "",
      "url": "/debian-nonfree",
      "status": "S1737720178X1737763378",
      "upstream": "rsync://mirrors.tuna.tsinghua.edu.cn/debian-nonfree/",
      "help": "",
      "size": "43.40G"
    },
    {
      "cname": "debian-security",
      "desc": "",
      "url": "/debian-security",
      "status": "S1737723415X1737766615",
      "upstream": "rsync://mirrors.tuna.tsinghua.edu.cn/debian-security/",
      "help": "",
      "size": "295.48G"
    },
    {
      "cname": "docker-ce",
      "desc": "",
      "url": "/docker-ce",
      "status": "S1737721138X1737764338",
      "upstream": "rsync://mirrors.tuna.tsinghua.edu.cn/docker-ce/",
      "help": "",
      "size": "1.20T"
    },
    {
      "cname": "epel",
      "desc": "",
      "url": "/epel",
      "status": "S1737723560X1737766760",
      "upstream": "rsync://mirrors.tuna.tsinghua.edu.cn/epel/",
      "help": "",
      "size": "481.17G"
    },
    {
      "cname": "fedora",
      "desc": "",
      "url": "/fedora",
      "status": "S1737683203X1737726403",
      "upstream": "rsync://mirrors.tuna.tsinghua.edu.cn/fedora/",
      "help": "",
      "size": "1.87T"
    },
    {
      "cname": "gentoo",
      "desc": "",
      "url": "/gentoo",
      "status": "S1737723938X1737767138",
      "upstream": "rsync://mirrors.tuna.tsinghua.edu.cn/gentoo/",
      "help": "",
      "size": "829.68G"
    },
    {
      "cname": "homebrew-bottles",
      "desc": "",
      "url": "/homebrew-bottles",
      "status": "S1737723113X1737766313",
      "upstream": "rsync://mirrors.tuna.tsinghua.edu.cn/homebrew-bottles/",
      "help": "",
      "size": "534.27G"
    },
    {
      "cname": "kali",
      "desc": "",
      "url": "/kali",
      "status": "S1737685443X1737728643",
      "upstream": "rsync://mirrors.tuna.tsinghua.edu.cn/kali/",
      "help": "",
      "size": "640.21G"
    },
    {
      "cname": "kali-images",
      "desc": "",
      "url": "/kali-images",
      "status": "S1737721523X1737764723",
      "upstream": "rsync://mirrors.tuna.tsinghua.edu.cn/kali-images/",
      "help": "",
      "size": "160.35G"
    },
    {
      "cname": "linuxmint",
      "desc": "",
      "url": "/linuxmint",
      "status": "S1737720892X1737764092",
      "upstream": "rsync://mirrors.tuna.tsinghua.edu.cn/linuxmint/",
      "help": "",
      "size": "42.80G"
    },
    {
      "cname": "linuxmint-cd",
      "desc": "",
      "url": "/linuxmint-cd",
      "status": "S1737720066X1737763266",
      "upstream": "rsync://mirrors.tuna.tsinghua.edu.cn/linuxmint-cd/",
      "help": "",
      "size": "123.95G"
    },
    {
      "cname": "putty",
      "desc": "",
      "url": "/putty",
      "status": "S1737720133X1737763333",
      "upstream": "rsync://mirrors.tuna.tsinghua.edu.cn/putty/",
      "help": "",
      "size": "79.56M"
    },
    {
      "cname": "raspbian",
      "desc": "",
      "url": "/raspbian",
      "status": "S1737686558X1737729758",
      "upstream": "rsync://mirrors.tuna.tsinghua.edu.cn/raspbian/",
      "help": "",
      "size": "649.03G"
    },
    {
      "cname": "rocky",
      "desc": "",
      "url": "/rocky",
      "status": "S1737690972X1737734172",
      "upstream": "rsync://msync.rockylinux.org/rocky-linux/",
      "help": "",
      "size": "1.86T"
    },
    {
      "cname": "ubuntu",
      "desc": "",
      "url": "/ubuntu",
      "status": "S1737710131X1737753331",
      "upstream": "rsync://mirrors.bfsu.edu.cn/ubuntu/",
      "help": "",
      "size": "3.09T"
    },
    {
      "cname": "ubuntu-cdimage",
      "desc": "",
      "url": "/ubuntu-cdimage",
      "status": "S1737720052X1737763252",
      "upstream": "rsync://mirrors.tuna.tsinghua.edu.cn/ubuntu-cdimage/",
      "help": "",
      "size": "876.31G"
    },
    {
      "cname": "ubuntu-ports",
      "desc": "",
      "url": "/ubuntu-ports",
      "status": "S1737710828X1737754028",
      "upstream": "rsync://rsync.mirrors.ustc.edu.cn/ubuntu-ports/",
      "help": "",
      "size": "3.65T"
    },
    {
      "cname": "ubuntu-releases",
      "desc": "",
      "url": "/ubuntu-releases",
      "status": "S1737720118X1737763318",
      "upstream": "rsync://mirrors.tuna.tsinghua.edu.cn/ubuntu-releases/",
      "help": "",
      "size": "42.57G"
    }
  ]
}